{
  "type": "科幻末世",
  "date": "2026-06-29",
  "prev_date": "2026-06-28",
  "category": {
    "name": "科幻末世",
    "trend": {
      "new_count": 1,
      "dropped_count": 1,
      "new_books": [
        "游戏入侵：每秒永久涨一点生命值"
      ],
      "dropped_books": [
        {
          "title": "上交火星，国家把我宠上天",
          "intro": "陈宇穿越火星，濒死之际绑定【文明先驱系统】。 反手把反重力推进器上交国家： “祖国养我，我还祖国一个火星行政区！” 从那天起，华夏全境开启科技大爆发！ 送去保暖衣，换回量子芯片！ 送去烤鸭，换回核聚变"
        }
      ],
      "top_risers": [
        {
          "title": "别再求生了，我真没觉醒炉鼎天赋",
          "change": "+6"
        },
        {
          "title": "全民垂钓：开局百万倍SSS天赋",
          "change": "+2"
        },
        {
          "title": "末世车队：我能消融任何代价",
          "change": "+2"
        }
      ],
      "top_fallers": [
        {
          "title": "绝望都市：解锁女明星就获得资源",
          "change": "-3"
        },
        {
          "title": "公路求生：开局搭档校花后妈",
          "change": "-3"
        },
        {
          "title": "末世：厌男校花她真没想服从啊",
          "change": "-2"
        }
      ],
      "reads_growth": [
        {
          "title": "小区求生：每人每天给我一块面包",
          "growth": "+1.8万"
        },
        {
          "title": "地心求生：我给全服写攻略",
          "growth": "+1.1万"
        },
        {
          "title": "列车求生，我开宝箱百倍暴击",
          "growth": "+1.0万"
        }
      ],
      "summary": "**🔥 题材趋势** “全民求生”框架成为绝对主流，并细分为“小区求生”“列车求生”“海岛求生”等多个子赛道。《小区求生：每人每天给我一块面包》以“包租公”模式领跑。**📖 读者偏好** 读者对“天降系统/天赋暴击”的爽点需求强烈，如《序列求生：我可以无限附加词条》《全民垂钓：开局百万倍SSS天赋》。同时，“多女主+杀伐果断”标准配置依然是头部作品的标配。**🆕 新上榜作品** 《游戏入侵：每秒永久涨一点生命值》以“每秒涨生命上限”的新颖天赋机制切入，属于“反套路”的数值成长流，具有差异化优势。**📉 掉出榜单** 《上交火星，国家把我宠上天》的“家国情怀”题材与榜单主流的“个人求生/后宫”画风差异较大，受众重叠度低。**💡 值得关注** 《别再求生了，我真没觉醒炉鼎天赋》排名飙升6位，其“炉鼎”设定虽老，但巧妙结合“末世双修”与“负面标签”的营销点，成功吸引了眼球。"
    },
    "books": [
      {
        "title": "小区求生：每人每天给我一块面包",
        "author": "吴忠贤",
        "reads": "16.6万",
        "intro": "【全民塔防发育+升级小窝+稳重+非常多女主+奴隶主】 “每人开局只有一间10平米的房间，一瓶水，一个面包，3金币，以及一次随机抽取天赋的机会。” “想活下去吗？想明白人生的真正意义吗？那就拼尽一切收集物资，升级你的房间，为你的房间加装武器！提升你的天赋，努力活下去！” 全人类永夜求生。 陈岸开局抽到唯一天赋，唯我独尊！ 【唯我独尊（lv1）：你将自动绑定你所在的小区内的所有人，只要他们存活，你每天都可以从每人的身上获得一份随机奖励】 【今日奖励已刷新：面包×1000000】 第一天面包。 第二天纯净水。 第三天武器。 第四天…… 当其他住户还在永夜里拼命与怪物搏杀，获取升级房间的物资时，陈岸却已经喝着香槟，搂着不同类型的女神开始了享受。 “感谢永夜世界，我现在已经明白了人生的意义！” 陈岸如实说道。",
        "cover": "https://p3-reading-sign.fqnovelpic.com/novel-pic/p2oe68583e10d6d922189bbeb74f3692248~tplv-resize:225:0.image?lk3s=5b7047ff&x-expires=1783312205&x-signature=uLnbb1CFk3iTUoAt8py2BCuxoFk%3D",
        "url": "https://fanqienovel.com/page/7632258300507065406"
      },
      {
        "title": "地心求生：我给全服写攻略",
        "author": "至日不眠",
        "reads": "13.6万",
        "intro": "【求生游戏】【挖矿与打造】【深入地心】【泰拉瑞亚】【矿车升级】 蓝星全民被卷入求生游戏，每人一辆简陋矿车，不断向地心深处探索，可能挖到有用的矿石，也可能是危险的怪物…… 好在林幽觉醒神级攻略系统，只要撰写攻略、获得好评，就能收获超级奖励！ 于是，林幽走上了一条助人为乐的开挂之路！",
        "cover": "https://p3-reading-sign.fqnovelpic.com/novel-pic/p2oba5f82cc27bfa1b709df03574c50610b~tplv-resize:225:0.image?lk3s=5b7047ff&x-expires=1783312205&x-signature=%2FZmCPvM%2BlTs4iiFH1Wanl67fs50%3D",
        "url": "https://fanqienovel.com/page/7641981074850974745"
      },
      {
        "title": "列车求生，我开宝箱百倍暴击",
        "author": "奶油黄瓜西红柿",
        "reads": "8.9万",
        "intro": "林牧一觉醒来进入了列车求生游戏，并觉醒了SSS级天赋，好感度暴击。 【宝箱开启】 【获得物品：A级技能卡】 【国民仙子，大明星苏清漓对你的好感度九十，触发好感度暴击，暴击倍率九十倍】 【获得物品：A级技能卡九十张。】 【技能卡叠加可升级。】 于是林牧将收获的大量技能卡不断叠加，C级升B级，B级升A级，A级升S级。 明明是在C级站点，别人还只能拿到C级技能，他已经用上了A级技能，甚至S级技能。 再加上物资暴击，经验值暴击。 别人的等级还是十几级，他已经七八十级了。 别人的列车还是一级二级，他的列车也已经升到了四五级。 什么大明星啊，美女老师啊，学妹校花啊，应有尽有。 PS：本书主打开宝箱暴击，主角横推一切，多女主，不喜勿入。",
        "cover": "https://p3-reading-sign.fqnovelpic.com/novel-pic/p2o5e5e212401a9bbb1a56d034a4f6eec47~tplv-resize:225:0.image?lk3s=5b7047ff&x-expires=1783312205&x-signature=9ZKGyW2x1rEYd6iaqZH60Ecw3zM%3D",
        "url": "https://fanqienovel.com/page/7646445571842001945"
      },
      {
        "title": "小区求生：肾化危机？不！是天堂",
        "author": "猫尾的笔呀",
        "reads": "8.2万",
        "intro": "【求生】【刺激】【超凡】【小区穿越】【不圣母】 小区外面居然变了模样。 原本高耸的大楼和人来人往的街道，变成了一片汪洋海洋。 天空之上还有两个太阳，汽车大小的螃蟹、比水桶还粗的海蟒，以人为猎物的巨型蜘蛛……",
        "cover": "https://p3-reading-sign.fqnovelpic.com/novel-pic/p2o1e56c4d9e0bfbea3be958635f4eefb66~tplv-resize:225:0.image?lk3s=5b7047ff&x-expires=1783312205&x-signature=tG6PXKAtuNssEb0h5WYPDa%2FuB4Y%3D",
        "url": "https://fanqienovel.com/page/7635654037215382590"
      },
      {
        "title": "全民垂钓：开局百万倍SSS天赋",
        "author": "当歌kk",
        "reads": "8万",
        "intro": "【垂钓+多女主+冒险+杀伐果断不圣母+有脑+无敌绝不憋屈+横推流+嘎嘎乱杀+美女如云】 林北穿越到一个千百年前，世界天河倒灌，从此开启全民垂钓大时代的世界！ 海里能钓起诸天至宝，上古神鱼，作为资深钓鱼佬，林北以为稳了，然而却遇天崩开局，成了这个世界贫民窟碧波号上的一名低等杂鱼！ 虽然有个美女舍友，但只能看不能碰啊！ 好在关键时刻，系统激活，等等……百万倍垂钓天赋是什么鬼？ 从此，画风变得不对劲了。 “什么叫钓史诗级至宝，太古神鳞和吃饭喝水一样简单？” “什么叫林北那小子又又又刷屏了？” “王德发？什么叫林北把上古神鲲钓起来了？” “什么叫鲲之大一锅炖不下？？林北，你小子不会打算吃上古神兽吧！” “什么叫东海第一美女为了吃一口，主动给林北投怀送抱？” “牛逼！我不活了！” 本书又名：《关于我的垂钓物全来自上古那些事儿》《关于我在海上垂钓，一路从东杀到西那些事儿！》《钓钓钓，钓空四海！》",
        "cover": "https://p3-reading-sign.fqnovelpic.com/novel-pic/p2obc3e46fed75e35359b649fd93d58e804~tplv-resize:225:0.image?lk3s=5b7047ff&x-expires=1783312205&x-signature=PTzcghRspTl1fcvi66AxXU6KWY0%3D",
        "url": "https://fanqienovel.com/page/7647639655755566142"
      },
      {
        "title": "全女班：左拳高伤害，右拳伤害高",
        "author": "浮世石",
        "reads": "7.6万",
        "intro": "【多女主】+【杀伐果断】+【不死女】+【不圣母】+【多子多福】+【极致的属性碾压】 全球年满18岁至60岁的六十亿人，被按照单位扔进了地铁。 地铁每天停靠站点，补给物资，遭遇怪物。 三十七个女生就我一个男的，车辆觉醒协议：生命的延续！ 每次双方全属性永久飙升！ 陆渊更是激活天赋：绝对暴击（SSS） 倍率：1~100倍！ 经验暴击，属性暴击，掉落暴击，甚至是繁衍的属性！ 一次暴击就是几百！ 我叫陆渊。 末日降临的第一天，我成了全车厢最稀缺的战略资源。 【书不是你们那样写的！】",
        "cover": "https://p3-reading-sign.fqnovelpic.com/novel-pic/p2od62c1a7eb98c47dac0f8c13e0e8fcef2~tplv-resize:225:0.image?lk3s=5b7047ff&x-expires=1783312205&x-signature=UEeAKrsyf4NzeCMtdIU%2B1%2FWDSeg%3D",
        "url": "https://fanqienovel.com/page/7643817850821413912"
      },
      {
        "title": "序列求生：我可以无限附加词条",
        "author": "离群的独狼",
        "reads": "7.8万",
        "intro": "穿越那天，林默以为自己中了头彩。 金手指、美人膝、天下权，他连孩子的名字都想好了。 可惜，命运递来的不是彩票，而是地狱的门票。 诡异降临，城市沦为怪物的乐园。 残余的幸存者们像野狗一样在满是诡异的世界艰难求存。 而林默就是其中之一。",
        "cover": "https://p9-reading-sign.fqnovelpic.com/novel-pic/p2oc9d6348fb9fedfb49a575297771c991c~tplv-resize:225:0.image?lk3s=5b7047ff&x-expires=1783312205&x-signature=ony8Yj0Wetg7MfbeGbVCtAdY%2FFs%3D",
        "url": "https://fanqienovel.com/page/7635546923297934361"
      },
      {
        "title": "末世家庭求生，我家人口世界第一",
        "author": "墨色染尽流年",
        "reads": "5.9万",
        "intro": "【多女+末世塔防+家庭求生+多子多福】 “末世游戏降临，请所有人以家庭为单位努力活下去。” “家庭人数最低为2人，最多不限。人口越多，遭受的袭击压力越大，但后期可能获得的积分和奖励也越多。” “家是你的港湾，请保护好你的家。” 曹爽一觉醒来，就发现自己出现在陌生的小区陌生的房间。 全民家庭求生？ 可我激活末世多子多福系统是什么鬼？ 好吧，能力越大责任越大，你们不要的女神我来守护。 可单亲妈妈什么鬼？ 什么？不够？再来一个肚中带球主动上门。 别的家庭苦哈哈求生。 可曹爽看着一屋子美女和幼崽，愁的只挠头——自己一个人陪不过来啊！",
        "cover": "https://p3-reading-sign.fqnovelpic.com/novel-pic/p2o0cd1d2aa2de30ba6e85e950be94e8fdf~tplv-resize:225:0.image?lk3s=5b7047ff&x-expires=1783312205&x-signature=X26fjYHwTcNkFAcw1qyzaMN%2FjQ8%3D",
        "url": "https://fanqienovel.com/page/7628967740467858456"
      },
      {
        "title": "别再求生了，我真没觉醒炉鼎天赋",
        "author": "远古老剑修",
        "reads": "5.9万",
        "intro": "又名：《末日求生，双修使我无限强化》 【求生/身穿/契约/多女/不圣母/杀伐果断】 末日丧尸，荒野迷雾，公路列车求生，宿舍极限塔防，疯狂海岛世界…… 故事从警花姐妹绑架姜辰开始，她们自称重生者。 大明星苏依菲来迟一步，愤怒曝光姜辰觉醒S级天赋双修炉鼎，能让女玩家异能进化，并且儿女全都S级！ 全球女玩家开始疯了…… 没人知道，姜辰是个穿越者，他觉醒的并非S级而是SSSR级纯阳道体，并且还有一个薪火传承（开枝散叶）系统。 宇宙开启生灭轮回，各族生灵寻求超脱； 求生游戏降临后，姜辰走上了属于他的超凡之路……",
        "cover": "https://p3-reading-sign.fqnovelpic.com/novel-pic/p2o2b618c2d11b52cbc568e63fd8aafcec7~tplv-resize:225:0.image?lk3s=5b7047ff&x-expires=1783312205&x-signature=47yWs4w%2Fln%2FRXerE%2BmHegqJUYUU%3D",
        "url": "https://fanqienovel.com/page/7647825296325889086"
      },
      {
        "title": "全民海岛：开局SSS级命运抽卡",
        "author": "苍梧墨渊",
        "reads": "5.8万",
        "intro": "【求生+抽卡+无敌+经营+争霸+后宫】 全球百亿人穿越海上孤岛。 一人一岛，资源有限，弱肉强食。 穿越的第一天，萧初南就认清了一个事实。 这个世界不存在公平，不存在善良，只存在资源和暴力。 于是他做了三件事。 第一，垄断熟食，饿死同行。 第二，囤积道具，坐地起价。 第三，养兵蓄力，定点清除。 有人骂他奸商，他加价。 有人威胁他，他记名字。 有人扬言组队来打他，他直接传送过去端了对方老巢。 \"你们在频道里骂得挺欢的时候，有没有想过一个问题？\" \"我凭什么要对你们客气？\" 全服通报一次又一次挂出他的名字。 各区高玩咬牙切齿：萧初南，你到底开了什么挂？",
        "cover": "https://p3-reading-sign.fqnovelpic.com/novel-pic/p2o8192eb7bcc9d9e2073c75da5ca6f2300~tplv-resize:225:0.image?lk3s=5b7047ff&x-expires=1783312205&x-signature=LSHuJv7%2BgfyFLM%2BbKE6qBLUZnjY%3D",
        "url": "https://fanqienovel.com/page/7638840392070204440"
      },
      {
        "title": "末世：厌男校花她真没想服从啊",
        "author": "李安澜OVO",
        "reads": "5.4万",
        "intro": "【丧尸、多女、异能、升级、利己】 经典开局，不喜勿入～ 江野重生归来，手刃兵部司令的儿子。 你说治安员？我有君临异能，通通给我跪下！ …… 在这秩序崩坏、变异生物横行的末世，人类渺小如蚁。 江野依靠着前世的经验，不断提升体质，成为人类最强的男人。 丧尸全杀了！ 变异生物全杀了！ 敢惹他的人也全部碾杀！ 至于漂亮的妹子……",
        "cover": "https://p3-reading-sign.fqnovelpic.com/novel-pic/p2o75400311a69e99d6e6000f33d18e1c08~tplv-resize:225:0.image?lk3s=5b7047ff&x-expires=1783312208&x-signature=v7qLhjUa0ZbrAMaUIjoOjeB%2Fqdk%3D",
        "url": "https://fanqienovel.com/page/7646540791413738521"
      },
      {
        "title": "全民列车求生：我开局绑定骸骨号",
        "author": "小诡在人间",
        "reads": "5.3万",
        "intro": "【求生】、【囤货】、【升级列车】、【克苏鲁元素】 一觉醒来，全球几十亿人被困在一列永不停止的求生列车上。 身后，死亡蠕虫穷追不舍，一旦被追上，就是尸骨无存。 好在每人开局都有一辆专属列车。 有人抽到钢铁战争号，武装到牙齿，火力全开。 有人抽到女仆号，魅魔天使任你召唤，爽到起飞。 有人抽到极光号，快如闪电，来去如风。 而悍匪出身的林浔，看着眼前这辆由森森白骨拼成的列车，陷入了沉思。 “骸骨号……这他妈能跑赢虫子？” 直到深夜，寂静车厢里传来低语。 车窗外，巨大的不可名状之物在黑暗中缓缓睁眼。 林浔发现，自己的列车，好像不只是“交通工具”那么简单。 它饿。 （含克系元素，主角全程高压求生，无轻松度假，非爽文模板，慎入。）",
        "cover": "https://p3-reading-sign.fqnovelpic.com/novel-pic/p2o3952bede46dc17f7915e7b585092afcf~tplv-resize:225:0.image?lk3s=5b7047ff&x-expires=1783312208&x-signature=CsiySsuHOllDrO%2BwP4Bh6T4olMI%3D",
        "url": "https://fanqienovel.com/page/7642929771667524633"
      },
      {
        "title": "绝望都市：解锁女明星就获得资源",
        "author": "一只要溺死的鱼",
        "reads": "5.3万",
        "intro": "王昊都不知道自己死了多少次，终于明白自己的金手指是什么，原来他是一把万能钥匙，只要每天解锁女明星都可以获得物资，每天解锁的人数越多，获得物资的倍数等于当时人数。 为了能在这诡异的都市里活下来，主动收集跟他一样流落在此的女明星，来自全世界的女明星也不知死了多少次，遇到王昊之后才走摆脱死亡漩涡，生存的压力驱使她们一起合作。 希望她们人多力量大，能走出这片被亚空间能量，所影响的超级都市吧［微笑］",
        "cover": "https://p3-reading-sign.fqnovelpic.com/novel-pic/p2of3c1e6693bce0d4c71f81f7a8510760d~tplv-resize:225:0.image?lk3s=5b7047ff&x-expires=1783312208&x-signature=WejIM8xYcewY%2FcrDVRYlwQr1%2Fdw%3D",
        "url": "https://fanqienovel.com/page/7639014737895771161"
      },
      {
        "title": "木筏求生，开局捡到大蜜蜜",
        "author": "陆小鸡",
        "reads": "5.2万",
        "intro": "【海上求生+载具升级+游戏+女明星++无敌+反派+冷血+杀伐果断】 全民穿越海上求生，开局一艘破烂木筏，每人有一次抽取天赋的机会。 王旭抽到海神天赋，招募船员就能变强，无限背包，每秒产出物资。 开局捡到娱乐圈顶流小花大蜜蜜。 【恭喜你成功招募一名船员！】 【每秒物资获取+2】 【全属性提升+100%】 …… 从此，别人求生，他享受人生。 别人辛辛苦苦收集物资，他只要安心躺平就行。 （你想看见谁，请在评论区留下你的小爪爪。）",
        "cover": "https://p3-reading-sign.fqnovelpic.com/novel-pic/p2od82a2fe7317bf4642a1b2be978ec6621~tplv-resize:225:0.image?lk3s=5b7047ff&x-expires=1783312208&x-signature=m%2FFqzM5VVNKZOWApYjVCILLf8NI%3D",
        "url": "https://fanqienovel.com/page/7636215750918687769"
      },
      {
        "title": "末世车队：我能消融任何代价",
        "author": "听月月月月月月",
        "reads": "5.2万",
        "intro": "【车队+系统+多女主+小队模式】 主角前期弱，无脑文，有毒点，不喜勿入。 末世来临，诡异降临人间，人类被迫过上了迁徙的生活，有一支车队在末世中缓慢前行着。 诡物使用代价太大，你无法接受？ 序列代价太大，折磨的你精神崩溃？ 什么，你说你残废了活不下去？ 来找我，只要你能付得起价格。 其他车队的诡物不值钱，是因为他们承受不起诡物使用的代价。我们车队的诡物这么值钱，是因为没有代价。 哦，对不起，说的不全面。 不单是诡物没代价，甚至序列都没有代价。",
        "cover": "https://p3-reading-sign.fqnovelpic.com/novel-pic/p2o422b71d74f58086386ff6bf58a66cbe5~tplv-resize:225:0.image?lk3s=5b7047ff&x-expires=1783312208&x-signature=zQS%2BiOrpLDCXr%2BG5A3sYOFlOdmo%3D",
        "url": "https://fanqienovel.com/page/7646785128085064729"
      },
      {
        "title": "末日来袭，我赶着小毛驴逃命",
        "author": "挨打就立正",
        "reads": "5万",
        "intro": "末日来袭，各种诡异在吃人，在寻找避难所的路上，我只有一个小毛驴。 “我去，那是个驴车吗？” “那头驴怎么比诡异还凶？”",
        "cover": "https://p3-reading-sign.fqnovelpic.com/novel-pic/p2o3d034f3340665c6dfff8aa50376f3593~tplv-resize:225:0.image?lk3s=5b7047ff&x-expires=1783312208&x-signature=3r%2Fk1srDtIDZw9wJJN%2F8OjJcv4g%3D",
        "url": "https://fanqienovel.com/page/7641898741657504830"
      },
      {
        "title": "公路求生：开局搭档校花后妈",
        "author": "江灯明火",
        "reads": "5万",
        "intro": "【公路求生+诡异+载具升级+多女+杀伐果断+爽文】 一觉醒来，曹明穿越到公路求生的世界。 身边躺着的绝美少妇，竟然是校花的后妈？ 开局抽到SSS级生存天赋，还意外觉醒全服唯一隐藏天赋：【神级队友】。 绑定九星队友，每日躺收物资宝箱！ 当队友好感度达到100，日后还能再抽取一项新的生存天赋！ 这岂止是不输在起跑线，这简直就是在起跑线上起飞啊！ 一路冒险杀怪的同时，各路九星女神，接连加入他的车队： 美艳少妇、纯情校花、反差总裁、健身教练…… 牛仔裤、黑丝袜、职业套装、瑜伽裤…… 队友越多，宝箱越多，抽取的天赋就越多！ 当其他求生者还在为生存物资发愁，为各种诡异怪物发抖时，曹明已经躺在豪华房车里，左拥右抱，享受美好人生了。",
        "cover": "https://p3-reading-sign.fqnovelpic.com/novel-pic/p2of4b0c8928967e61f7d596ca0d213ea60~tplv-resize:225:0.image?lk3s=5b7047ff&x-expires=1783312208&x-signature=EUsLoEwY35p7nfayF4lkfwjtZf0%3D",
        "url": "https://fanqienovel.com/page/7590658471033326616"
      },
      {
        "title": "海洋集装箱求生：我靠MC登神",
        "author": "exaeqe",
        "reads": "5万",
        "intro": "无cp+主角二穿+正常心理，不冷酷，也不圣母 +麦块 玩集装箱求生突发奇想开的书，在里面加了点克系元素和一些杂七杂八的设定，欢迎品鉴，主角半无敌。 白泽在围观MC最新版本的时候挂了，穿越到了崩溃的蓝星上，还没反应过来就又穿了。 伟大的蓝星意志把蓝星人民都转移到了新世界，避免了和蓝星一起湮灭。 一人一个集装箱，在这个未知的世界活下去吧。 MC模组：神化，水产品2，tacz，乐事系列模组等等 对于MC物品的属性部分会魔改，不完全遵照游戏里的设定。",
        "cover": "https://p3-reading-sign.fqnovelpic.com/novel-pic/p2oa4787128d6040754986fecbcd5719df9~tplv-resize:225:0.image?lk3s=5b7047ff&x-expires=1783312208&x-signature=VeX6ATawMZNGLA7CPF%2FxFwZtHjk%3D",
        "url": "https://fanqienovel.com/page/7634543663057488920"
      },
      {
        "title": "游戏入侵：每秒永久涨一点生命值",
        "author": "雪糕的神",
        "reads": "4.6万",
        "intro": "【末日不圣母+无敌+万人敌+遥遥领先+杀伐果断+单女主】 　　重生前，苏沉的天赋是每秒回复1点血，全服公认的垃圾。 　　重生后，天赋变异了：每秒涨1点生命值上限！ 　　于是末日画风突变： 　　第一天，苏沉拿石头冲进了怪物群，顶着怪物杀了个七进七出。 　　第三天，苏沉生命值破十万，站着让精英怪啃，结果它把自己牙崩碎了。 　　....... 　　第七天，灾厄BOSS打了苏沉半天，发现对方血条都没掉，直言究竟你是BOSS还是我是BOSS？ 　　...... 　　曾经背叛苏沉的女友和兄弟，此刻正缩在墙角看苏沉表演。 　　直到苏沉在末日世界打造出了最强安全区的时候。 　　前女友颤抖着问：“苏沉，我错了！我们复合吧！我以后一定对你好的！” 　　但发现为时已晚，苏沉的周围早已被明星，女神，校花给团团包围。 　　苏沉顶着【Lv.1】的头衔，血条显示【+∞】。 　　他弹了弹指甲里的灰，面前是十大神魔BOSS【Lv.999】。 　　“要不，你们一起上？我赶时间。”",
        "cover": "https://p3-reading-sign.fqnovelpic.com/novel-pic/p2o5ee989d91a32c44bafdcc85e0bbd0981~tplv-resize:225:0.image?lk3s=5b7047ff&x-expires=1783312208&x-signature=ExLaZRRQ8aAHT7sDNX4OkpSsFMo%3D",
        "url": "https://fanqienovel.com/page/7646338529911376958"
      },
      {
        "title": "全民狩猎求生：我的猎犬是东北虎",
        "author": "九粒元宵",
        "reads": "4.5万",
        "intro": "【全民求生】＋【极寒】＋【狩猎】＋【无敌开局】＋【猛兽猎犬】＋【多女主】＋【合作捕猎】 一觉醒来，几十亿人进入全球狩猎求生世界。 开局每人两条狗，装备都靠打。 别人的猎犬是哈士奇、藏獒、职业斗犬，张启开局就是两只巅峰东北虎！！！ …… 极寒、饥饿、极端天气、野兽、变异生物...... 这是一个社会崩塌、律法崩坏、物资匮乏、充满黑暗和暴力的极寒模式世界。 想要获得更好的食物，更好的生活，唯有依靠更大的拳头，更强的猎犬捕猎。 在这里，哪怕是最弱的兔子，依旧长得比狗还大，可以轻松解决人类。 …… 【成年东北虎】＋【巅峰极限个体】＝天生杀戮机器，杀戮怪兽，锁喉瞬杀！ 【极限北极熊】＋【狩猎重甲】＝一掌拍死，绝对防御！ 当其他人为了一只兔子，在斩杀线疯狂挣扎的时候。 张启已经坐在老阴币专属豪华雪橇中，一边涮着火锅，一边指挥着猛兽猎犬疯狂乱杀。 ..... 从两只极限东北虎，到极限北极熊。 从各司其职的【狩猎小队】，到暴力征伐的【巅峰狩猎军团】。 只要张启敢想，蛟龙也杀给你看。",
        "cover": "https://p3-reading-sign.fqnovelpic.com/novel-pic/p2o9ca2de10eb4a7a852d3fb044cab412a3~tplv-resize:225:0.image?lk3s=5b7047ff&x-expires=1783312208&x-signature=IEWzVsBSx9PyIBUJCI1Sow8r43Q%3D",
        "url": "https://fanqienovel.com/page/7609665770775120921"
      }
    ]
  },
  "categories": [
    {
      "name": "科幻末世",
      "trend": {
        "new_count": 1,
        "dropped_count": 1,
        "new_books": [
          "游戏入侵：每秒永久涨一点生命值"
        ],
        "dropped_books": [
          {
            "title": "上交火星，国家把我宠上天",
            "intro": "陈宇穿越火星，濒死之际绑定【文明先驱系统】。 反手把反重力推进器上交国家： “祖国养我，我还祖国一个火星行政区！” 从那天起，华夏全境开启科技大爆发！ 送去保暖衣，换回量子芯片！ 送去烤鸭，换回核聚变"
          }
        ],
        "top_risers": [
          {
            "title": "别再求生了，我真没觉醒炉鼎天赋",
            "change": "+6"
          },
          {
            "title": "全民垂钓：开局百万倍SSS天赋",
            "change": "+2"
          },
          {
            "title": "末世车队：我能消融任何代价",
            "change": "+2"
          }
        ],
        "top_fallers": [
          {
            "title": "绝望都市：解锁女明星就获得资源",
            "change": "-3"
          },
          {
            "title": "公路求生：开局搭档校花后妈",
            "change": "-3"
          },
          {
            "title": "末世：厌男校花她真没想服从啊",
            "change": "-2"
          }
        ],
        "reads_growth": [
          {
            "title": "小区求生：每人每天给我一块面包",
            "growth": "+1.8万"
          },
          {
            "title": "地心求生：我给全服写攻略",
            "growth": "+1.1万"
          },
          {
            "title": "列车求生，我开宝箱百倍暴击",
            "growth": "+1.0万"
          }
        ],
        "summary": "**🔥 题材趋势** “全民求生”框架成为绝对主流，并细分为“小区求生”“列车求生”“海岛求生”等多个子赛道。《小区求生：每人每天给我一块面包》以“包租公”模式领跑。**📖 读者偏好** 读者对“天降系统/天赋暴击”的爽点需求强烈，如《序列求生：我可以无限附加词条》《全民垂钓：开局百万倍SSS天赋》。同时，“多女主+杀伐果断”标准配置依然是头部作品的标配。**🆕 新上榜作品** 《游戏入侵：每秒永久涨一点生命值》以“每秒涨生命上限”的新颖天赋机制切入，属于“反套路”的数值成长流，具有差异化优势。**📉 掉出榜单** 《上交火星，国家把我宠上天》的“家国情怀”题材与榜单主流的“个人求生/后宫”画风差异较大，受众重叠度低。**💡 值得关注** 《别再求生了，我真没觉醒炉鼎天赋》排名飙升6位，其“炉鼎”设定虽老，但巧妙结合“末世双修”与“负面标签”的营销点，成功吸引了眼球。"
      },
      "books": [
        {
          "title": "小区求生：每人每天给我一块面包",
          "author": "吴忠贤",
          "reads": "16.6万",
          "intro": "【全民塔防发育+升级小窝+稳重+非常多女主+奴隶主】 “每人开局只有一间10平米的房间，一瓶水，一个面包，3金币，以及一次随机抽取天赋的机会。” “想活下去吗？想明白人生的真正意义吗？那就拼尽一切收集物资，升级你的房间，为你的房间加装武器！提升你的天赋，努力活下去！” 全人类永夜求生。 陈岸开局抽到唯一天赋，唯我独尊！ 【唯我独尊（lv1）：你将自动绑定你所在的小区内的所有人，只要他们存活，你每天都可以从每人的身上获得一份随机奖励】 【今日奖励已刷新：面包×1000000】 第一天面包。 第二天纯净水。 第三天武器。 第四天…… 当其他住户还在永夜里拼命与怪物搏杀，获取升级房间的物资时，陈岸却已经喝着香槟，搂着不同类型的女神开始了享受。 “感谢永夜世界，我现在已经明白了人生的意义！” 陈岸如实说道。",
          "cover": "https://p3-reading-sign.fqnovelpic.com/novel-pic/p2oe68583e10d6d922189bbeb74f3692248~tplv-resize:225:0.image?lk3s=5b7047ff&x-expires=1783312205&x-signature=uLnbb1CFk3iTUoAt8py2BCuxoFk%3D",
          "url": "https://fanqienovel.com/page/7632258300507065406"
        },
        {
          "title": "地心求生：我给全服写攻略",
          "author": "至日不眠",
          "reads": "13.6万",
          "intro": "【求生游戏】【挖矿与打造】【深入地心】【泰拉瑞亚】【矿车升级】 蓝星全民被卷入求生游戏，每人一辆简陋矿车，不断向地心深处探索，可能挖到有用的矿石，也可能是危险的怪物…… 好在林幽觉醒神级攻略系统，只要撰写攻略、获得好评，就能收获超级奖励！ 于是，林幽走上了一条助人为乐的开挂之路！",
          "cover": "https://p3-reading-sign.fqnovelpic.com/novel-pic/p2oba5f82cc27bfa1b709df03574c50610b~tplv-resize:225:0.image?lk3s=5b7047ff&x-expires=1783312205&x-signature=%2FZmCPvM%2BlTs4iiFH1Wanl67fs50%3D",
          "url": "https://fanqienovel.com/page/7641981074850974745"
        },
        {
          "title": "列车求生，我开宝箱百倍暴击",
          "author": "奶油黄瓜西红柿",
          "reads": "8.9万",
          "intro": "林牧一觉醒来进入了列车求生游戏，并觉醒了SSS级天赋，好感度暴击。 【宝箱开启】 【获得物品：A级技能卡】 【国民仙子，大明星苏清漓对你的好感度九十，触发好感度暴击，暴击倍率九十倍】 【获得物品：A级技能卡九十张。】 【技能卡叠加可升级。】 于是林牧将收获的大量技能卡不断叠加，C级升B级，B级升A级，A级升S级。 明明是在C级站点，别人还只能拿到C级技能，他已经用上了A级技能，甚至S级技能。 再加上物资暴击，经验值暴击。 别人的等级还是十几级，他已经七八十级了。 别人的列车还是一级二级，他的列车也已经升到了四五级。 什么大明星啊，美女老师啊，学妹校花啊，应有尽有。 PS：本书主打开宝箱暴击，主角横推一切，多女主，不喜勿入。",
          "cover": "https://p3-reading-sign.fqnovelpic.com/novel-pic/p2o5e5e212401a9bbb1a56d034a4f6eec47~tplv-resize:225:0.image?lk3s=5b7047ff&x-expires=1783312205&x-signature=9ZKGyW2x1rEYd6iaqZH60Ecw3zM%3D",
          "url": "https://fanqienovel.com/page/7646445571842001945"
        },
        {
          "title": "小区求生：肾化危机？不！是天堂",
          "author": "猫尾的笔呀",
          "reads": "8.2万",
          "intro": "【求生】【刺激】【超凡】【小区穿越】【不圣母】 小区外面居然变了模样。 原本高耸的大楼和人来人往的街道，变成了一片汪洋海洋。 天空之上还有两个太阳，汽车大小的螃蟹、比水桶还粗的海蟒，以人为猎物的巨型蜘蛛……",
          "cover": "https://p3-reading-sign.fqnovelpic.com/novel-pic/p2o1e56c4d9e0bfbea3be958635f4eefb66~tplv-resize:225:0.image?lk3s=5b7047ff&x-expires=1783312205&x-signature=tG6PXKAtuNssEb0h5WYPDa%2FuB4Y%3D",
          "url": "https://fanqienovel.com/page/7635654037215382590"
        },
        {
          "title": "全民垂钓：开局百万倍SSS天赋",
          "author": "当歌kk",
          "reads": "8万",
          "intro": "【垂钓+多女主+冒险+杀伐果断不圣母+有脑+无敌绝不憋屈+横推流+嘎嘎乱杀+美女如云】 林北穿越到一个千百年前，世界天河倒灌，从此开启全民垂钓大时代的世界！ 海里能钓起诸天至宝，上古神鱼，作为资深钓鱼佬，林北以为稳了，然而却遇天崩开局，成了这个世界贫民窟碧波号上的一名低等杂鱼！ 虽然有个美女舍友，但只能看不能碰啊！ 好在关键时刻，系统激活，等等……百万倍垂钓天赋是什么鬼？ 从此，画风变得不对劲了。 “什么叫钓史诗级至宝，太古神鳞和吃饭喝水一样简单？” “什么叫林北那小子又又又刷屏了？” “王德发？什么叫林北把上古神鲲钓起来了？” “什么叫鲲之大一锅炖不下？？林北，你小子不会打算吃上古神兽吧！” “什么叫东海第一美女为了吃一口，主动给林北投怀送抱？” “牛逼！我不活了！” 本书又名：《关于我的垂钓物全来自上古那些事儿》《关于我在海上垂钓，一路从东杀到西那些事儿！》《钓钓钓，钓空四海！》",
          "cover": "https://p3-reading-sign.fqnovelpic.com/novel-pic/p2obc3e46fed75e35359b649fd93d58e804~tplv-resize:225:0.image?lk3s=5b7047ff&x-expires=1783312205&x-signature=PTzcghRspTl1fcvi66AxXU6KWY0%3D",
          "url": "https://fanqienovel.com/page/7647639655755566142"
        },
        {
          "title": "全女班：左拳高伤害，右拳伤害高",
          "author": "浮世石",
          "reads": "7.6万",
          "intro": "【多女主】+【杀伐果断】+【不死女】+【不圣母】+【多子多福】+【极致的属性碾压】 全球年满18岁至60岁的六十亿人，被按照单位扔进了地铁。 地铁每天停靠站点，补给物资，遭遇怪物。 三十七个女生就我一个男的，车辆觉醒协议：生命的延续！ 每次双方全属性永久飙升！ 陆渊更是激活天赋：绝对暴击（SSS） 倍率：1~100倍！ 经验暴击，属性暴击，掉落暴击，甚至是繁衍的属性！ 一次暴击就是几百！ 我叫陆渊。 末日降临的第一天，我成了全车厢最稀缺的战略资源。 【书不是你们那样写的！】",
          "cover": "https://p3-reading-sign.fqnovelpic.com/novel-pic/p2od62c1a7eb98c47dac0f8c13e0e8fcef2~tplv-resize:225:0.image?lk3s=5b7047ff&x-expires=1783312205&x-signature=UEeAKrsyf4NzeCMtdIU%2B1%2FWDSeg%3D",
          "url": "https://fanqienovel.com/page/7643817850821413912"
        },
        {
          "title": "序列求生：我可以无限附加词条",
          "author": "离群的独狼",
          "reads": "7.8万",
          "intro": "穿越那天，林默以为自己中了头彩。 金手指、美人膝、天下权，他连孩子的名字都想好了。 可惜，命运递来的不是彩票，而是地狱的门票。 诡异降临，城市沦为怪物的乐园。 残余的幸存者们像野狗一样在满是诡异的世界艰难求存。 而林默就是其中之一。",
          "cover": "https://p9-reading-sign.fqnovelpic.com/novel-pic/p2oc9d6348fb9fedfb49a575297771c991c~tplv-resize:225:0.image?lk3s=5b7047ff&x-expires=1783312205&x-signature=ony8Yj0Wetg7MfbeGbVCtAdY%2FFs%3D",
          "url": "https://fanqienovel.com/page/7635546923297934361"
        },
        {
          "title": "末世家庭求生，我家人口世界第一",
          "author": "墨色染尽流年",
          "reads": "5.9万",
          "intro": "【多女+末世塔防+家庭求生+多子多福】 “末世游戏降临，请所有人以家庭为单位努力活下去。” “家庭人数最低为2人，最多不限。人口越多，遭受的袭击压力越大，但后期可能获得的积分和奖励也越多。” “家是你的港湾，请保护好你的家。” 曹爽一觉醒来，就发现自己出现在陌生的小区陌生的房间。 全民家庭求生？ 可我激活末世多子多福系统是什么鬼？ 好吧，能力越大责任越大，你们不要的女神我来守护。 可单亲妈妈什么鬼？ 什么？不够？再来一个肚中带球主动上门。 别的家庭苦哈哈求生。 可曹爽看着一屋子美女和幼崽，愁的只挠头——自己一个人陪不过来啊！",
          "cover": "https://p3-reading-sign.fqnovelpic.com/novel-pic/p2o0cd1d2aa2de30ba6e85e950be94e8fdf~tplv-resize:225:0.image?lk3s=5b7047ff&x-expires=1783312205&x-signature=X26fjYHwTcNkFAcw1qyzaMN%2FjQ8%3D",
          "url": "https://fanqienovel.com/page/7628967740467858456"
        },
        {
          "title": "别再求生了，我真没觉醒炉鼎天赋",
          "author": "远古老剑修",
          "reads": "5.9万",
          "intro": "又名：《末日求生，双修使我无限强化》 【求生/身穿/契约/多女/不圣母/杀伐果断】 末日丧尸，荒野迷雾，公路列车求生，宿舍极限塔防，疯狂海岛世界…… 故事从警花姐妹绑架姜辰开始，她们自称重生者。 大明星苏依菲来迟一步，愤怒曝光姜辰觉醒S级天赋双修炉鼎，能让女玩家异能进化，并且儿女全都S级！ 全球女玩家开始疯了…… 没人知道，姜辰是个穿越者，他觉醒的并非S级而是SSSR级纯阳道体，并且还有一个薪火传承（开枝散叶）系统。 宇宙开启生灭轮回，各族生灵寻求超脱； 求生游戏降临后，姜辰走上了属于他的超凡之路……",
          "cover": "https://p3-reading-sign.fqnovelpic.com/novel-pic/p2o2b618c2d11b52cbc568e63fd8aafcec7~tplv-resize:225:0.image?lk3s=5b7047ff&x-expires=1783312205&x-signature=47yWs4w%2Fln%2FRXerE%2BmHegqJUYUU%3D",
          "url": "https://fanqienovel.com/page/7647825296325889086"
        },
        {
          "title": "全民海岛：开局SSS级命运抽卡",
          "author": "苍梧墨渊",
          "reads": "5.8万",
          "intro": "【求生+抽卡+无敌+经营+争霸+后宫】 全球百亿人穿越海上孤岛。 一人一岛，资源有限，弱肉强食。 穿越的第一天，萧初南就认清了一个事实。 这个世界不存在公平，不存在善良，只存在资源和暴力。 于是他做了三件事。 第一，垄断熟食，饿死同行。 第二，囤积道具，坐地起价。 第三，养兵蓄力，定点清除。 有人骂他奸商，他加价。 有人威胁他，他记名字。 有人扬言组队来打他，他直接传送过去端了对方老巢。 \"你们在频道里骂得挺欢的时候，有没有想过一个问题？\" \"我凭什么要对你们客气？\" 全服通报一次又一次挂出他的名字。 各区高玩咬牙切齿：萧初南，你到底开了什么挂？",
          "cover": "https://p3-reading-sign.fqnovelpic.com/novel-pic/p2o8192eb7bcc9d9e2073c75da5ca6f2300~tplv-resize:225:0.image?lk3s=5b7047ff&x-expires=1783312205&x-signature=LSHuJv7%2BgfyFLM%2BbKE6qBLUZnjY%3D",
          "url": "https://fanqienovel.com/page/7638840392070204440"
        },
        {
          "title": "末世：厌男校花她真没想服从啊",
          "author": "李安澜OVO",
          "reads": "5.4万",
          "intro": "【丧尸、多女、异能、升级、利己】 经典开局，不喜勿入～ 江野重生归来，手刃兵部司令的儿子。 你说治安员？我有君临异能，通通给我跪下！ …… 在这秩序崩坏、变异生物横行的末世，人类渺小如蚁。 江野依靠着前世的经验，不断提升体质，成为人类最强的男人。 丧尸全杀了！ 变异生物全杀了！ 敢惹他的人也全部碾杀！ 至于漂亮的妹子……",
          "cover": "https://p3-reading-sign.fqnovelpic.com/novel-pic/p2o75400311a69e99d6e6000f33d18e1c08~tplv-resize:225:0.image?lk3s=5b7047ff&x-expires=1783312208&x-signature=v7qLhjUa0ZbrAMaUIjoOjeB%2Fqdk%3D",
          "url": "https://fanqienovel.com/page/7646540791413738521"
        },
        {
          "title": "全民列车求生：我开局绑定骸骨号",
          "author": "小诡在人间",
          "reads": "5.3万",
          "intro": "【求生】、【囤货】、【升级列车】、【克苏鲁元素】 一觉醒来，全球几十亿人被困在一列永不停止的求生列车上。 身后，死亡蠕虫穷追不舍，一旦被追上，就是尸骨无存。 好在每人开局都有一辆专属列车。 有人抽到钢铁战争号，武装到牙齿，火力全开。 有人抽到女仆号，魅魔天使任你召唤，爽到起飞。 有人抽到极光号，快如闪电，来去如风。 而悍匪出身的林浔，看着眼前这辆由森森白骨拼成的列车，陷入了沉思。 “骸骨号……这他妈能跑赢虫子？” 直到深夜，寂静车厢里传来低语。 车窗外，巨大的不可名状之物在黑暗中缓缓睁眼。 林浔发现，自己的列车，好像不只是“交通工具”那么简单。 它饿。 （含克系元素，主角全程高压求生，无轻松度假，非爽文模板，慎入。）",
          "cover": "https://p3-reading-sign.fqnovelpic.com/novel-pic/p2o3952bede46dc17f7915e7b585092afcf~tplv-resize:225:0.image?lk3s=5b7047ff&x-expires=1783312208&x-signature=CsiySsuHOllDrO%2BwP4Bh6T4olMI%3D",
          "url": "https://fanqienovel.com/page/7642929771667524633"
        },
        {
          "title": "绝望都市：解锁女明星就获得资源",
          "author": "一只要溺死的鱼",
          "reads": "5.3万",
          "intro": "王昊都不知道自己死了多少次，终于明白自己的金手指是什么，原来他是一把万能钥匙，只要每天解锁女明星都可以获得物资，每天解锁的人数越多，获得物资的倍数等于当时人数。 为了能在这诡异的都市里活下来，主动收集跟他一样流落在此的女明星，来自全世界的女明星也不知死了多少次，遇到王昊之后才走摆脱死亡漩涡，生存的压力驱使她们一起合作。 希望她们人多力量大，能走出这片被亚空间能量，所影响的超级都市吧［微笑］",
          "cover": "https://p3-reading-sign.fqnovelpic.com/novel-pic/p2of3c1e6693bce0d4c71f81f7a8510760d~tplv-resize:225:0.image?lk3s=5b7047ff&x-expires=1783312208&x-signature=WejIM8xYcewY%2FcrDVRYlwQr1%2Fdw%3D",
          "url": "https://fanqienovel.com/page/7639014737895771161"
        },
        {
          "title": "木筏求生，开局捡到大蜜蜜",
          "author": "陆小鸡",
          "reads": "5.2万",
          "intro": "【海上求生+载具升级+游戏+女明星++无敌+反派+冷血+杀伐果断】 全民穿越海上求生，开局一艘破烂木筏，每人有一次抽取天赋的机会。 王旭抽到海神天赋，招募船员就能变强，无限背包，每秒产出物资。 开局捡到娱乐圈顶流小花大蜜蜜。 【恭喜你成功招募一名船员！】 【每秒物资获取+2】 【全属性提升+100%】 …… 从此，别人求生，他享受人生。 别人辛辛苦苦收集物资，他只要安心躺平就行。 （你想看见谁，请在评论区留下你的小爪爪。）",
          "cover": "https://p3-reading-sign.fqnovelpic.com/novel-pic/p2od82a2fe7317bf4642a1b2be978ec6621~tplv-resize:225:0.image?lk3s=5b7047ff&x-expires=1783312208&x-signature=m%2FFqzM5VVNKZOWApYjVCILLf8NI%3D",
          "url": "https://fanqienovel.com/page/7636215750918687769"
        },
        {
          "title": "末世车队：我能消融任何代价",
          "author": "听月月月月月月",
          "reads": "5.2万",
          "intro": "【车队+系统+多女主+小队模式】 主角前期弱，无脑文，有毒点，不喜勿入。 末世来临，诡异降临人间，人类被迫过上了迁徙的生活，有一支车队在末世中缓慢前行着。 诡物使用代价太大，你无法接受？ 序列代价太大，折磨的你精神崩溃？ 什么，你说你残废了活不下去？ 来找我，只要你能付得起价格。 其他车队的诡物不值钱，是因为他们承受不起诡物使用的代价。我们车队的诡物这么值钱，是因为没有代价。 哦，对不起，说的不全面。 不单是诡物没代价，甚至序列都没有代价。",
          "cover": "https://p3-reading-sign.fqnovelpic.com/novel-pic/p2o422b71d74f58086386ff6bf58a66cbe5~tplv-resize:225:0.image?lk3s=5b7047ff&x-expires=1783312208&x-signature=zQS%2BiOrpLDCXr%2BG5A3sYOFlOdmo%3D",
          "url": "https://fanqienovel.com/page/7646785128085064729"
        },
        {
          "title": "末日来袭，我赶着小毛驴逃命",
          "author": "挨打就立正",
          "reads": "5万",
          "intro": "末日来袭，各种诡异在吃人，在寻找避难所的路上，我只有一个小毛驴。 “我去，那是个驴车吗？” “那头驴怎么比诡异还凶？”",
          "cover": "https://p3-reading-sign.fqnovelpic.com/novel-pic/p2o3d034f3340665c6dfff8aa50376f3593~tplv-resize:225:0.image?lk3s=5b7047ff&x-expires=1783312208&x-signature=3r%2Fk1srDtIDZw9wJJN%2F8OjJcv4g%3D",
          "url": "https://fanqienovel.com/page/7641898741657504830"
        },
        {
          "title": "公路求生：开局搭档校花后妈",
          "author": "江灯明火",
          "reads": "5万",
          "intro": "【公路求生+诡异+载具升级+多女+杀伐果断+爽文】 一觉醒来，曹明穿越到公路求生的世界。 身边躺着的绝美少妇，竟然是校花的后妈？ 开局抽到SSS级生存天赋，还意外觉醒全服唯一隐藏天赋：【神级队友】。 绑定九星队友，每日躺收物资宝箱！ 当队友好感度达到100，日后还能再抽取一项新的生存天赋！ 这岂止是不输在起跑线，这简直就是在起跑线上起飞啊！ 一路冒险杀怪的同时，各路九星女神，接连加入他的车队： 美艳少妇、纯情校花、反差总裁、健身教练…… 牛仔裤、黑丝袜、职业套装、瑜伽裤…… 队友越多，宝箱越多，抽取的天赋就越多！ 当其他求生者还在为生存物资发愁，为各种诡异怪物发抖时，曹明已经躺在豪华房车里，左拥右抱，享受美好人生了。",
          "cover": "https://p3-reading-sign.fqnovelpic.com/novel-pic/p2of4b0c8928967e61f7d596ca0d213ea60~tplv-resize:225:0.image?lk3s=5b7047ff&x-expires=1783312208&x-signature=EUsLoEwY35p7nfayF4lkfwjtZf0%3D",
          "url": "https://fanqienovel.com/page/7590658471033326616"
        },
        {
          "title": "海洋集装箱求生：我靠MC登神",
          "author": "exaeqe",
          "reads": "5万",
          "intro": "无cp+主角二穿+正常心理，不冷酷，也不圣母 +麦块 玩集装箱求生突发奇想开的书，在里面加了点克系元素和一些杂七杂八的设定，欢迎品鉴，主角半无敌。 白泽在围观MC最新版本的时候挂了，穿越到了崩溃的蓝星上，还没反应过来就又穿了。 伟大的蓝星意志把蓝星人民都转移到了新世界，避免了和蓝星一起湮灭。 一人一个集装箱，在这个未知的世界活下去吧。 MC模组：神化，水产品2，tacz，乐事系列模组等等 对于MC物品的属性部分会魔改，不完全遵照游戏里的设定。",
          "cover": "https://p3-reading-sign.fqnovelpic.com/novel-pic/p2oa4787128d6040754986fecbcd5719df9~tplv-resize:225:0.image?lk3s=5b7047ff&x-expires=1783312208&x-signature=VeX6ATawMZNGLA7CPF%2FxFwZtHjk%3D",
          "url": "https://fanqienovel.com/page/7634543663057488920"
        },
        {
          "title": "游戏入侵：每秒永久涨一点生命值",
          "author": "雪糕的神",
          "reads": "4.6万",
          "intro": "【末日不圣母+无敌+万人敌+遥遥领先+杀伐果断+单女主】 　　重生前，苏沉的天赋是每秒回复1点血，全服公认的垃圾。 　　重生后，天赋变异了：每秒涨1点生命值上限！ 　　于是末日画风突变： 　　第一天，苏沉拿石头冲进了怪物群，顶着怪物杀了个七进七出。 　　第三天，苏沉生命值破十万，站着让精英怪啃，结果它把自己牙崩碎了。 　　....... 　　第七天，灾厄BOSS打了苏沉半天，发现对方血条都没掉，直言究竟你是BOSS还是我是BOSS？ 　　...... 　　曾经背叛苏沉的女友和兄弟，此刻正缩在墙角看苏沉表演。 　　直到苏沉在末日世界打造出了最强安全区的时候。 　　前女友颤抖着问：“苏沉，我错了！我们复合吧！我以后一定对你好的！” 　　但发现为时已晚，苏沉的周围早已被明星，女神，校花给团团包围。 　　苏沉顶着【Lv.1】的头衔，血条显示【+∞】。 　　他弹了弹指甲里的灰，面前是十大神魔BOSS【Lv.999】。 　　“要不，你们一起上？我赶时间。”",
          "cover": "https://p3-reading-sign.fqnovelpic.com/novel-pic/p2o5ee989d91a32c44bafdcc85e0bbd0981~tplv-resize:225:0.image?lk3s=5b7047ff&x-expires=1783312208&x-signature=ExLaZRRQ8aAHT7sDNX4OkpSsFMo%3D",
          "url": "https://fanqienovel.com/page/7646338529911376958"
        },
        {
          "title": "全民狩猎求生：我的猎犬是东北虎",
          "author": "九粒元宵",
          "reads": "4.5万",
          "intro": "【全民求生】＋【极寒】＋【狩猎】＋【无敌开局】＋【猛兽猎犬】＋【多女主】＋【合作捕猎】 一觉醒来，几十亿人进入全球狩猎求生世界。 开局每人两条狗，装备都靠打。 别人的猎犬是哈士奇、藏獒、职业斗犬，张启开局就是两只巅峰东北虎！！！ …… 极寒、饥饿、极端天气、野兽、变异生物...... 这是一个社会崩塌、律法崩坏、物资匮乏、充满黑暗和暴力的极寒模式世界。 想要获得更好的食物，更好的生活，唯有依靠更大的拳头，更强的猎犬捕猎。 在这里，哪怕是最弱的兔子，依旧长得比狗还大，可以轻松解决人类。 …… 【成年东北虎】＋【巅峰极限个体】＝天生杀戮机器，杀戮怪兽，锁喉瞬杀！ 【极限北极熊】＋【狩猎重甲】＝一掌拍死，绝对防御！ 当其他人为了一只兔子，在斩杀线疯狂挣扎的时候。 张启已经坐在老阴币专属豪华雪橇中，一边涮着火锅，一边指挥着猛兽猎犬疯狂乱杀。 ..... 从两只极限东北虎，到极限北极熊。 从各司其职的【狩猎小队】，到暴力征伐的【巅峰狩猎军团】。 只要张启敢想，蛟龙也杀给你看。",
          "cover": "https://p3-reading-sign.fqnovelpic.com/novel-pic/p2o9ca2de10eb4a7a852d3fb044cab412a3~tplv-resize:225:0.image?lk3s=5b7047ff&x-expires=1783312208&x-signature=IEWzVsBSx9PyIBUJCI1Sow8r43Q%3D",
          "url": "https://fanqienovel.com/page/7609665770775120921"
        }
      ]
    }
  ]
}