{
  "type": "都市高武",
  "date": "2026-07-17",
  "prev_date": "2026-07-16",
  "category": {
    "name": "都市高武",
    "trend": {
      "new_count": 4,
      "dropped_count": 4,
      "new_books": [
        "高武：我岩王帝君，专治各种不服",
        "我开启的宝箱品质永远加3",
        "觉醒异能，我把自己上交国家",
        "国运拼哥：我大帝修为被妹妹曝光"
      ],
      "dropped_books": [
        {
          "title": "天幕让你当废物班长你独断万古？",
          "intro": "【新题材+全网首发+群像+爽+甜+全员老六】 【评分刚出后续会涨，请放心食用。】 叶楚昊穿越至异界，历经亿万年修成无敌仙帝，无聊之下回归原点，成了全国公认最差班级，高三（9）班的废柴班长。 　　本想收"
        },
        {
          "title": "全球异能：开局觉醒七大原罪分身",
          "intro": "评分刚出，后面会...算了涨不涨我也不知道，先看再说！ 【灵气复苏】【杀伐果断】【不圣母】【腹黑】【分身】 这是人族最为璀璨的时代，人族立于万界之颠，所有世界，都是猎场，也是资源！ 林白穿越而来，本以"
        },
        {
          "title": "我一正经邪神，只接受合法献祭",
          "intro": "（评分刚出+无敌流+大一新生+乐子仙人+高调之神+三清列仙出没） 【肌肉男】【社畜】【大明星】【零】 某天，大一新生陈川发现，人们头上出现一个个这样的词条。 而他，可以自由买卖这些词条。 或者说是，献"
        },
        {
          "title": "觉醒序列孙大圣，二郎学姐太撩了",
          "intro": "【剧情流】+【非无脑爽】+【神话序列】 霓虹与钢铁的阴影里，他们的厮杀从未停止。 　　在这座城市的背面，怪物们伪装成人，以血肉为食；天幕的深处，旧神们垂下眼眸，冷眼旁观。 　　灾域与现世的交错中，哪一"
        }
      ],
      "top_risers": [
        {
          "title": "造化工厂：保卫科个个是神魔！",
          "change": "+4"
        },
        {
          "title": "契约不了机娘？内燃机了解一下",
          "change": "+3"
        },
        {
          "title": "国术：从被武警搜山击毙开始见神",
          "change": "+1"
        }
      ],
      "top_fallers": [
        {
          "title": "假面骑士的我，还是抱错的真少爷",
          "change": "-2"
        },
        {
          "title": "异兽入侵：我编造了铠甲救世组织",
          "change": "-2"
        },
        {
          "title": "我才三岁，怎么会是灭世级灾厄",
          "change": "-1"
        }
      ],
      "reads_growth": [
        {
          "title": "第一次破译免费？反手破译系统！",
          "growth": "+1.0万"
        },
        {
          "title": "我都宇宙之主了，你们还在地球？",
          "growth": "+9000"
        },
        {
          "title": "国术：从被武警搜山击毙开始见神",
          "growth": "+6000"
        }
      ],
      "summary": "**🔥 题材趋势**  \n「国运直播+系统金手指」仍是绝对主流（《国运拼哥》《第一次破译免费》等7本），「修仙与高武融合」扎堆（晚年大帝、岩王帝君、真少爷修仙），「无敌流+情绪爽点」成为"
    },
    "books": [
      {
        "title": "我都宇宙之主了，你们还在地球？",
        "author": "吒牛",
        "reads": "37.9万",
        "intro": "徐缺觉醒了金手指，获得了天赋抽取能力！ 天赋一：【长生不老】每天增加1年寿命，无上限。 天赋二：【逆天悟性】每天增加1点悟性，无上限。 天赋三：【百倍暴击】每天修炼进度百倍暴击！ 天赋四：【你的命就是我的命】每斩杀一人，获得一条命，无上限。 天赋五：【我自带泉水】每秒恢复1%的任何伤势。 天赋六：【一念诸天】自由往来无数位面。 天赋七：…… ………… 【姓名：徐缺】 【代号：混沌】 【档案密级：绝密】 【危险等级：SSS（？？？）】 【目标常态：外表为普通青年男性，无明显超凡特征，日常行为模式与常人无异】 【已观测能力清单（不完全统计）】 【1：具体实力不详，但肉体横渡虚空，硬扛核弹，无视一切现有科技】 【2：X年 X月，第一头SSS级妖皇复苏，高62米，长116米，片刻后，这头巨兽疑似被目标击杀，举世哗然！】 【3：X年X月，数十头超越妖皇的存在复苏，末日降临……】 【4：……】 【998：该死！他自杀了？不对，他怎么又活了？】 【999：他居然是不死的！】 【警告：目标极其危险，极其危险，极其危险，不可贸然接触，接触极易触发不可控后果！】 【建议：全面监控，严禁一切形式的主动接触，所有主动接触者，以叛国罪，反人类罪论处！】",
        "cover": "https://p3-reading-sign.fqnovelpic.com/novel-pic/p2o96c2eeca26d8cbcc3fd8f54f7cd3ae5f~tplv-resize:225:0.image?lk3s=5b7047ff&x-expires=1784835795&x-signature=xHLlaNsfTPIVL73JjvgwduQuOCo%3D",
        "url": "https://fanqienovel.com/page/7644040936980220953"
      },
      {
        "title": "第一次破译免费？反手破译系统！",
        "author": "我不吃牛肉c",
        "reads": "37.5万",
        "intro": "【诸天妖孽大舞台、卡bug、乐子文、癫】 宇宙升维考验开始，所有文明的智慧生物都要参与此次试炼，创造出打破这方宇宙极限的修炼体系… 蓝星也从此进入了全新时代。 林挽成为了第一批试炼者，每一次试炼，都将与整个宇宙所有智慧生命同台竞技。 他脑海多了个破译系统，可选择天地万物进行破译，破译后可获得其本源代码。 资源可实现量产！ 天赋、资质、修行感悟亦可取而代之！ 可破译需要破译点，破译点需要击杀智慧生命才能获得。 但是，第一次破译免费，无需消耗破译点。 林挽反手将第一次破译次数用来破译破译系统。 然后他系统直接乱码了。 【破译点：#@%¥】",
        "cover": "https://p3-reading-sign.fqnovelpic.com/novel-pic/p2oc07b0958d47f4b0d90fc6893dc4d45bb~tplv-resize:225:0.image?lk3s=5b7047ff&x-expires=1784835795&x-signature=8huMOwRA7jGnNNbqPnQ6J7b4xug%3D",
        "url": "https://fanqienovel.com/page/7633400795525811262"
      },
      {
        "title": "国运：沉睡棺中，八大阴将守华夏",
        "author": "浮云的云",
        "reads": "26万",
        "intro": "【国运+直播+阴门八将+师徒传承+爽文+群像】 国运游戏降临，全球各国随机选出九人守护国门。 华夏这边，八个\"守村人\"和一口漆黑棺材被传送进国运空间。 全网炸了！ \"完了！八个智障加一口破棺材，华夏要亡！\" \"其他国家都是特种兵、异能者，我们这是什么鬼阵容？\" \"建议直接投降，别浪费时间了……\" 然而，当第一波怪物攻城时—— 捞尸人一根竹竿，尸潮倒卷； 缝尸匠飞针走线，缝合怪物成傀儡； 赶尸匠铃铛一响，万鬼听令； 扎纸匠剪刀翻飞，纸人化军团； 棺材匠一锤定音,怪物当场暴毙； 唢呐匠一曲《百鸟朝凤》，送敌人上西天； 风水先生罗盘一转，改天换地； 刽子手鬼头刀出鞘，斩尽一切不详！ 全球震惊：\"这就是华夏的'智障'？\" 而那口黑棺中，沉睡着他们共同的师傅—— 阴门之主，苏晨。 \"徒儿们，为师先睡了，等华夏国运昌盛之日，便是为师出棺之时。\" \"在那之前，这国门……你们守得住吗？\" 八大阴将齐声：\"师傅放心，有我们在，华夏国门，固若金汤！\"",
        "cover": "https://p3-reading-sign.fqnovelpic.com/novel-pic/p2o52ce5b6ddb269f3f9c10a8d2a15890b4~tplv-resize:225:0.image?lk3s=5b7047ff&x-expires=1784835795&x-signature=uM5dtgE3OmonZfXu3XnyuN2N53I%3D",
        "url": "https://fanqienovel.com/page/7651928955489897534"
      },
      {
        "title": "晚年大帝，被妹妹召唤国运求生？",
        "author": "七十岁殿堂之资",
        "reads": "16.8万",
        "intro": "【国运求生+直播+诡异入侵+晚年大帝】 陆离穿越玄天界，帝路争锋，成为永夜魔帝。 万年后，举世皆寂，故人凋零，而他也步入了晚年。 这一日，他却听到了来自蓝星的血脉至亲，妹妹陆雪瑶的呼唤。 …… 龙国，749局觉醒仪式上，陆雪瑶召唤出哥哥陆离的投影，成为自己的本命诡宠。 这一日，国运游戏降临，每个国家随机挑选两个天选者，进入诡异世界求生。 只要在诡异世界中建立领地，就能抵挡诡异源头入侵现实世界。 选手死亡，将扣除本国国运，降临惩罚，选手在国运游戏中获得的资源，将有概率暴击返还给所在国家。 当其他天选者饥寒交迫，还在与诡异对抗，艰难求生时。 陆雪瑶在哥哥的指导下，已经在诡异世界中建立了无上魔国，万诡俯首，八方来朝。",
        "cover": "https://p3-reading-sign.fqnovelpic.com/novel-pic/p2o86548e72ba089a13387b0df3d6812494~tplv-resize:225:0.image?lk3s=5b7047ff&x-expires=1784835795&x-signature=q%2BiJqftBFoIAsmaeohiOBhjBNmI%3D",
        "url": "https://fanqienovel.com/page/7652308382908419096"
      },
      {
        "title": "国术：从被武警搜山击毙开始见神",
        "author": "四夕刂",
        "reads": "21.9万",
        "intro": "评分低是因为新书【龙蛇流】+【国术】+【民国】+【无系统】+【天才流】 陈洪武遭人陷害入狱三年，得奇人传授国术，出狱后明劲大成，却突闻噩耗—— 父母为自己奔走上诉劳碌而死！ 陈洪武怒上梁山，狂徒磨刀，管你权贵还是差人，皆要命丧拳下！ 咫尺之内，人尽敌国！ 挑战法律红线的陈洪武最终被武警部队击毙。 一朝醒来，却发现自己成了民国富少爷。 军阀割据、列强环伺！ 国术式微、妖魅魍魉横行！ 陈洪武重走武道之路，凭借铮铮铁拳，打出个煌煌大世！ 明劲、暗劲、化劲、丹劲、罡劲、金刚不坏、见神… 当陈洪武念头一动，滚滚天雷落下，面前钢铁巨舰化作铁水。 世人惊呼：这还是国术？",
        "cover": "https://p3-reading-sign.fqnovelpic.com/novel-pic/p2of3ec01a79dc5237e0b70cd764b83c1f6~tplv-resize:225:0.image?lk3s=5b7047ff&x-expires=1784835795&x-signature=fVnwLmQRRntHHIVkdGjHftHymbw%3D",
        "url": "https://fanqienovel.com/page/7647892624631680025"
      },
      {
        "title": "我才三岁，怎么会是灭世级灾厄",
        "author": "少喝冰镇饮料",
        "reads": "15.9万",
        "intro": "三年前，江洛穿越来到这个世界，成为一名刚出生的婴儿，并觉醒了【属性系统】。 系统告知他，这个世界很危险，但只要每存活一天，就能得到一个属性点。 江洛信了，小心翼翼活到了百日宴后，才发现这世界跟他前世的蓝星世界一模一样，从历史文化到科技发展，甚至时间线都没变，半点危险都看不到。 这让江洛以为，这有可能是个错位系统。 然而，当他两岁时的一次人前显圣失败后，他才发现，这系统根本屁用没有！ 就当江洛以为，这一生会平平淡淡的过下去时，一场突如其来的凶险，打碎他的安逸生活…… …… “灾厄？超凡者？诡异？凶兽？” “我去，狗系统你居然是对的？” 江洛彻底懵了。",
        "cover": "https://p3-reading-sign.fqnovelpic.com/novel-pic/p2oa421dbf8d89fa1129fc35612736958df~tplv-resize:225:0.image?lk3s=5b7047ff&x-expires=1784835795&x-signature=a8UPf3wYQVVtxeG%2Br7F%2Bd1OHUt0%3D",
        "url": "https://fanqienovel.com/page/7639494219232463897"
      },
      {
        "title": "本体SSS级，镜像也是SSS级",
        "author": "颜尽欢欢",
        "reads": "14.3万",
        "intro": "评分刚出！！！【SSS镜+单女主+无敌+快节奏+情绪路径】 　　 　　序列觉醒日，薄烬觉醒【梦魇】路径，世界上唯一的SSS级序列【镜】。 　　 　　技能包括但不限于：破镜之刃，折射，破碎，空间，武装。 　　 　　【镜中世界：倒映出一个初始面积为100平米的镜中世界，每一次升阶都可以提升镜的面积。】 　　 　　【双镜：映照出一个与本体一模一样的镜像，镜像与本体都是SSS级，且可以使用所有技能！】 　　 　　所有的序列者天才都震惊了。 　　 　　“这不是挂？！” 　　 　　“一个SSS级就已经很超标了，你居然有两个？！” 　 　　若干年后，堕落者攻陷了整个世界。 　　 　　“哈哈哈！” 　　 　　“序列者路边一条！” 　　 　　这时。 　　 　　一只遮天蔽日的手掌覆盖而来，整个世界变得一片黑暗。 　　“镜中世界！” 　　天外，或者说镜外。 　　 　　薄烬看着手中的镜面，其内倒映出无数堕落者所在的整个世界。 　　 　　下一刻。 　　 　　他手指轻轻一点。 　　 　　咔嚓。 　　 　　镜面破碎。 　　 　　整个世界也在这清澈的声响中随之破碎毁灭。",
        "cover": "https://p3-reading-sign.fqnovelpic.com/novel-pic/p2odc46ade11f117c5230b3f23454f1a4bd~tplv-resize:225:0.image?lk3s=5b7047ff&x-expires=1784835795&x-signature=hCFJAo48ZjvAGL8vqjZb28HuQSc%3D",
        "url": "https://fanqienovel.com/page/7650374971725728792"
      },
      {
        "title": "全民神祇时代：我的词条每日刷新",
        "author": "些许风霜过去",
        "reads": "17万",
        "intro": "陆胜穿越到了一个人人皆可成为神明，掌控法则，开辟小世界的超级世界。 主世界一天，小世界一年。 陆胜开局觉醒C级天赋词条【繁育之乡】，小世界内还有B级建筑【灵眼之泉】，妥妥的小天才一枚。 但没有人知道的是，陆胜还有一个X级天赋【词条之主】 主世界每天零点时间，他的小世界就会准时刷出一个新的词条！ 并且，以前拥有的词条不会消失！ 直到【融合】的词条出现，陆胜开始把拥有的词条一一融合…… C级【繁育之乡】+B级【多子多福】=S级资源词条【丰饶之巢】 D级【兽血沸腾】+A级【先天灵体】=SS级血脉词条【荒古灵兽身】 S级【演化加速】+A级【万物生长】=SSS级推演词条【时间掌握】 别人终其一生都只能获得一个天赋词条，而在陆胜这里，顶级词条随便批发！ ………… 【记载】：您的小世界灵气浓度提升百倍，子民修炼速度加快，高级资源出现的概率更高！ 【记载】：您的子民中已出现圣人级生物！ 【记载】：您已经攻破超大型神国，请尽快占领该世界，掠夺资源！ 当同龄人还在考虑省来的信仰点去买什么资源卡比较好，怎么培养自己的子民时—— 陆胜的小世界内已经人人成圣，建立仙朝，反攻异族神明了",
        "cover": "https://p3-reading-sign.fqnovelpic.com/novel-pic/p2oe4aa10d5cf17de514cb635315e38fef9~tplv-resize:225:0.image?lk3s=5b7047ff&x-expires=1784835795&x-signature=%2F7L%2Bn1t2Z%2BlNm67RFPPHPjo1LUM%3D",
        "url": "https://fanqienovel.com/page/7644794897249094718"
      },
      {
        "title": "变身：开局召唤铁幕，一击灭国运",
        "author": "螃蟹9527",
        "reads": "17.4万",
        "intro": "【前期国运+中期诸天万界+直播+性转+变身+变百+无敌+爽文+铁墓+崩铁……】 国运游戏入侵。 「苏亦晓选手运气爆棚！三枪打碎异族魂！」 「传奇狙击手苏亦晓还在猎杀！」 「天呐！苏亦晓选手转起来了！墙壁在开枪！墙壁在开枪！」 “别人都在老老实实攀科技，我直接转起来全秒了，就很，你懂吧？” …… 铁墓降临！ 高级文明：区区绝灭大君，我等必将令其燃烧！ 高级文明：？我家成矿了？ 顶级文明：区区铁墓，我等必将令其毁灭！ 顶级文明：？我家跌入混沌了？ 神级文明：这是不可跨越的鸿沟！毁灭于此！ 神级文明：？什么叫，你给我家锁了？ “别人都在老老实实玩国运游戏，就我来个铁墓给国运游戏炸了，就很，你懂吧？” …… 诸天万界。 天幻论道游戏。 别人：吾之剑道！无往不利！ 别人2：魔法！是我指尖跃动的信仰！ 别人3：科技至上！ 别人4：武道无穷！ 然后我：白昼与黑夜相等吗？义人与罪人相等吗？ 就很…… …… （后续包括但不限于黄金裔，星核猎手，幻胧，归寂，星啸，卡卡目，浮黎涟等等）",
        "cover": "https://p3-reading-sign.fqnovelpic.com/novel-pic/p2ob5a91611659882a2e4b1c2184499c012~tplv-resize:225:0.image?lk3s=5b7047ff&x-expires=1784835795&x-signature=a9%2BJpTjH0dXpbKYLI5Fw%2BpVWPqI%3D",
        "url": "https://fanqienovel.com/page/7652991563122887705"
      },
      {
        "title": "杀一怪叠一毒，我一人毒穿世界！",
        "author": "风样男子",
        "reads": "11.9万",
        "intro": "（评分刚出，后面会涨） 【全民+无限成长+无敌+稳重主角+爽爽爽】 游戏降临现实，全民转职时代开启。 　　苏尘觉醒了SSS级唯一隐藏职业——剧毒法师。 　　在这个别人下副本要死要活，面对高防高血Boss只能疯狂刮痧的时代，苏尘看着自己的职业特性陷入了沉思。 　　【特性1：你的任何攻击，强制为目标施加无法驱散的剧毒，每秒造成高额真实伤害。】 　　【特性2：你的毒素层数可无限叠加，每杀1个怪，上限+1。】 　　于是，画风变了。 　　别人眼里的毒法：刮痧、脆皮、没爆发。 苏尘眼里的毒法：卡机制、挂真伤、无限折磨！ 　　当其他天才还在为了一个首杀拼死拼活时。 　　苏尘只是对着深渊级BOSS平A了一下，然后转身找了个安全的地方坐下，开始悠闲地吃便当。 　　“别洗了，这debuff你洗不掉的。” 　　“血条长？那就多折磨你一会。” 　　多年后，当异界邪神降临，看着自己身上那几百万层无法驱散的剧毒，破防了：“这个毒系，怎么这么恶心啊？！” 　　苏尘无奈摊手：“我只是平A了一下，怎么全疯了？”",
        "cover": "https://p3-reading-sign.fqnovelpic.com/novel-pic/p2o74c49a7674387bb963be2790d7b935bf~tplv-resize:225:0.image?lk3s=5b7047ff&x-expires=1784835795&x-signature=2RvvmDjBmJXAEM9jd%2Bo98aDAjWY%3D",
        "url": "https://fanqienovel.com/page/7650816869128997912"
      },
      {
        "title": "黑暗拍卖会，开局拍下反派萝莉！",
        "author": "我吃姜丝",
        "reads": "8.4万",
        "intro": "【都市高武】【修仙】【反派】【轻松向】【多女主】【偏日常】 自从穿越而来，姜川一直以为自己过的是悠闲大少的日常生活，但万万没想到，老祖一出关就干死了八大家族。 姜川：“啊？原来我是反派命格吗？” 洛浅浅：“不，你不是反派！我才是！”",
        "cover": "https://p3-reading-sign.fqnovelpic.com/novel-pic/p2o0d953b5dc46da02aed9774a263db510c~tplv-resize:225:0.image?lk3s=5b7047ff&x-expires=1784835799&x-signature=Xz2TWDRTXzR%2B632ZSbnKg0Z9mm4%3D",
        "url": "https://fanqienovel.com/page/7649403749978344510"
      },
      {
        "title": "高武：不好了！真少爷是个修仙的",
        "author": "道友乱谈琴",
        "reads": "12.2万",
        "intro": "【评分刚出，后面会涨】 【全民高武我修仙，我笑别人看不穿】 林燃撞大运穿越到一个灵气复苏的高武世界，成了一个没能觉醒天赋的普通高中生。 并且，正在遭受一场围殴。 在这个强者为尊的世界，他一个没权没势，还没有天赋的孤儿，遭到欺凌似乎也很正常。 就当他快要被人打死的时候，发现了识海中的异常。 前世购买的一只青铜小鼎竟然随他穿越而来。 而此时，青铜小鼎之上正浮现出一部功法。 《万宝铸灵诀》，一部可以让没有灵根的人踏入仙途的逆天功法。 但是这功法每提升一个大境界，就需要炼化一件宝物。 好在识海中的青铜小鼎本身就是一件宝物，能够让他成功迈入炼气期。 借助青铜小鼎修复了伤势的林燃，趁势反击，将几名围殴他的人暴揍一顿。 原本应该算是正当防卫的他，又遭到保安的为难。 不出意外的话，意外出现了。 一对夫妇找到了他，并声称是他的亲生父母。 眨眼间，他又成了豪门流落在外的少爷。 前世操劳半生，也没享过什么福。 如今给他一个当少爷的机会，他却觉得索然无味。 都修仙了，谁还稀罕当什么豪门少爷？ “燃儿，我是你的亲生母亲啊！” “抱歉，这位女士，我们不熟。所以还是请你不要这样称呼我，那会让我觉得很不自在。”",
        "cover": "https://p3-reading-sign.fqnovelpic.com/novel-pic/p2o35a4a8690d00153ce01289cf8c0d74c3~tplv-resize:225:0.image?lk3s=5b7047ff&x-expires=1784835799&x-signature=EC5GMbMQ71lJ2G0WtN5mQ5esuxs%3D",
        "url": "https://fanqienovel.com/page/7645554869385825304"
      },
      {
        "title": "假面骑士的我，还是抱错的真少爷",
        "author": "我是快乐的人机",
        "reads": "8.4万",
        "intro": "【假面骑士+真少爷与结巴假千金+有骑士精神】（前面有一个穿越者小反派不过剧情不多不喜误进） 别人穿越，开局自带金手指系统。叶阳穿越，开局自带一台品红相机。上一世，叶阳的世界被怪兽入侵，命悬一线之际，帝骑和空我从天而降把他救了下来。事后所有人都说他是看特摄看魔怔了，差点把他送进精神病院。只有叶阳知道，自己作为全世界唯一记得真相的人，肯定摊上大事了。果然，转头就被一辆大运创飞。被创飞的一瞬间，他来到了一个白茫茫的空间，面前站着的正是那位路过的假面骑士。帝骑把同款品红相机递过来，并说道：骚年，你的旅途开始了。 而叶阳只来得及喊出一句：“你千万不要想不开去拍什么时王外传啊！会变成池塘守护者的！！”然后他就穿越了。新的人生，依旧被抱错，依旧孤儿院，依旧天崩开局。叶阳只想问帝骑哥一句：你穿越给我穿越好啊，倒是给我穿个好点的人家啊？ 结果事情越来越离谱—— 什么？我是林家大佬唯一的儿子？ 什么？我上面还有三个姐姐？ 什么？那个跟我抱错的假千金，居然是我网上聊了好几年的网友哥们？！ 叶阳举起相机，拍下了自己目瞪口呆的脸。 品红相机记录世界，而他负责在这操蛋又离谱的人生里，找到所有值得按下快门的瞬间。",
        "cover": "https://p3-reading-sign.fqnovelpic.com/novel-pic/p2o4fc35c26aeb89f641a6c7c1d7eaf6be3~tplv-resize:225:0.image?lk3s=5b7047ff&x-expires=1784835799&x-signature=y1Az%2BS%2BZr1%2B2aI5yZNvoTQWUizw%3D",
        "url": "https://fanqienovel.com/page/7652299898301205528"
      },
      {
        "title": "契约不了机娘？内燃机了解一下",
        "author": "飞雷神千鸟流",
        "reads": "11万",
        "intro": "【女主牢妹】【赛车竞技】【内燃机VS赛车机娘】 齐星开局被全险半挂做局，一代电竞天才少年就此陨落，穿越到文娱落后的机娘纪元世界，可重来一世还是造化弄人，大四的觉醒仪式上觉醒SSS级天赋却不能契约机娘？ “来小家伙，接受姐姐的怀抱吧” 齐星被S级机娘纪云棠看上，然而就在他与纪云棠连接精神链接的时候： 【检测到风险程序入侵，第三方强制契约失败！】 “无视风险继续安装！”齐星下意识脱口而出。 【安装失败，退出安装并删除！】。 齐星不死心接受契约失败的结果，接连与其他等级的机娘短暂邂逅，无一例外全是第三方强制契约失败，让他沦为全校的笑柄。 齐星：你说这扯不扯？先跳了，兄弟！ 就在他心灰意冷之下，被一个系统找上门，他可以在系统商城内够买前世所有类型的内燃机。 “系统，内燃机怎么跑得赢机娘？” 【科学的尽头是烧开水，武力的尽头是丢石子，如果机娘冒黑烟，那证明她已经到达了极限，而内燃机冒黑烟，说明它才刚刚发力。】 【你问内燃机凭什么赢？】 【因为钢铁不需要“爱”来驱动……】 【它只需要更粗的涡轮！更硬的凸轮轴！以及……】 【更多不怕死的疯子！】 【宿主，只要有钱，什么牛鬼蛇神都能买到。】",
        "cover": "https://p3-reading-sign.fqnovelpic.com/novel-pic/p2o3ff61f663a6f974f082704c5b865cd88~tplv-resize:225:0.image?lk3s=5b7047ff&x-expires=1784835799&x-signature=u0jPFgTSdeWpYSsOCDvahRGHyD8%3D",
        "url": "https://fanqienovel.com/page/7652027487576132632"
      },
      {
        "title": "造化工厂：保卫科个个是神魔！",
        "author": "大侠爱吃土豆",
        "reads": "10万",
        "intro": "林玄穿越高武世界，觉醒造化工厂系统，任何物品都可以被造化工厂解析，随后用最基础的材料制造出来。 “解析培灵丹，解析完成，持续输入灵气即可炼制！” 于是乎，林玄招募一万聚灵境底层人民，三班倒，日夜不停地在流水线输送灵气，源源不断的培灵丹被批量生产出来。 别的供货商卖三万联邦币一颗，林玄只卖三千！ “解析三品武器纳米战甲！解析完成，持续投入一品黑铁矿和聚灵境妖兽肉即可炼制。” 林玄反手又招募十万员工，开始日夜不停地炼制纳米战甲。 百宝阁卖上亿联邦币，林玄只卖一千万！ 百宝阁阁主脸色难看：“该死，这家伙炼制丹药武器不要成本的吗！？” “找人，弄死他！” “阁主，不好了！造化工厂的数十万工人暴动了，说咱们要是敢动林玄一根汗毛，他们就要灭了百宝阁！” “阁主，不好了！林玄说要搬走去其他城市，城首下令，三天之内咱们必须道歉，否则就要提供百万岗位承接造化工厂的工人。” “阁主，不好了！造化工厂的保卫科出动了，个个都是神魔，说是要在走之前把碍眼东西清理掉！” ………",
        "cover": "https://p3-reading-sign.fqnovelpic.com/novel-pic/p2o27dc0267604306732b0feba177deb045~tplv-resize:225:0.image?lk3s=5b7047ff&x-expires=1784835799&x-signature=Y6yPv%2BoNlqDWlZPR%2B5OwOCHaJZo%3D",
        "url": "https://fanqienovel.com/page/7647538764155210776"
      },
      {
        "title": "高武：我岩王帝君，专治各种不服",
        "author": "羽风无痕",
        "reads": "11.2万",
        "intro": "【每日10点更新，请大家准时期待！】 【评分刚出还有些低，看到我的在新书榜前30就知道不错了，值得入坑。】 这是一个异能觉醒的时代，虚空裂缝横跨苍穹，无数诡异生物降临人间。 林长歌穿越而来，在觉醒仪式上，意外加载了【岩王帝君·摩拉克斯】人物模板。 世人皆以为岩系异能只是平庸的防御，却不知林长歌眼中的世界早已不同。 “契约已成，食言者当受食岩之罚。” 他行走在城市边缘，随手一挥，玉璋护盾笼罩全城，任凭千万异兽轰炸，我自安如磐石。 当神级虚空之敌撕裂空间，人类防线全线溃败之际。 林长歌踏空而行，长枪划破长夜，双瞳闪烁着金色的神芒： “天动万象！” 那一夜，一颗千米陨石从高维坠落，将方圆百里化为石林，神明陨落！",
        "cover": "https://p3-reading-sign.fqnovelpic.com/novel-pic/p2o96e3506df38dae2021b109688a65b68b~tplv-resize:225:0.image?lk3s=5b7047ff&x-expires=1784835799&x-signature=TEJ08NLx6xin6KePclC2tpUUs50%3D",
        "url": "https://fanqienovel.com/page/7650143802287459352"
      },
      {
        "title": "我开启的宝箱品质永远加3",
        "author": "冒冒",
        "reads": "11.5万",
        "intro": "80多年前，超星游戏与现实融合，大量怪物冲击之下，人类只能建起高墙以阻挡怪物的入侵，幸好，玩家可以从游戏中获得实力和装备，带入现实，这才堪堪挡住了怪物的入侵。 在这里，年满18岁后，学校会统一组织进行觉醒仪式，只要觉醒天赋，就可以进入游戏，成为玩家，获取强大的实力。 林远是个穿越者，他居然……觉醒了两个天赋！ S级天赋【盾山】，你的体质永久提升200%。 还有等级不详、从来没有出现过的天赋【宝箱王】，你开启的所有宝箱，品质永远+3，并且开出的物品会强制适配你的等级。 林远以为自己要腾飞的时候，校长却带着他的企业家弟弟出现，甩出一张支票，想要购买他的天赋，移植给他觉醒失败的侄子，还发出了死亡威胁……",
        "cover": "https://p3-reading-sign.fqnovelpic.com/novel-pic/ai/p2o148efe28d582fc148d14fada15df2f56~tplv-resize:225:0.image?lk3s=5b7047ff&x-expires=1784835799&x-signature=HTREZt0yeXuMD%2FqdOJFO8mTagUQ%3D",
        "url": "https://fanqienovel.com/page/7657772314297109566"
      },
      {
        "title": "异兽入侵：我编造了铠甲救世组织",
        "author": "麦当劳打野",
        "reads": "8.1万",
        "intro": "【铠甲超凡+组织打造+半幕后+创造铠甲+异兽末世+无女主】 末世将至，异兽入侵！ 人类文明岌岌可危，现有的军事力量全面入侵之下两个小时机会文明毁灭！ 幸而周扬身穿水蓝星，携带“铠甲成真系统”降临这个世界。 只要他编造铠甲组织相关的剧情、故事、人设，就能影响别人的情绪，产生的特殊情绪越多，就能具现更多铠甲宇宙的神奇存在。 随后，一个名为“希光”的铠甲救世组织从时光的长河中浮现，一道道伟岸的身影在长河中熠熠生辉。 异兽浩劫，千年一次！ 而如今，是五千年一次的大劫！ 周扬：“我是希光组织的创建者，也是所有召唤人的导师！” 消防队长之子兼召唤人段炎正义凛然道：“你一天是异兽，你这辈子都会是异兽！” 清冷女总裁楚清月：“比钱赚钱，我更愿意成为一名召唤人！” 绝症患者王雷：“出招吧，反正你们都得死！” 一年后，浩劫降临，异兽全面入侵。 周扬领着希光组织所有成员，拿出召唤器，齐声高喊：“铠甲合体！” 异兽之神被打得神体黯淡碎成一段段的：“一个小星球，哪来的宇宙级强者！”",
        "cover": "https://p3-reading-sign.fqnovelpic.com/novel-pic/p2of2e1474061da4ab2c59daa69b369e4f0~tplv-resize:225:0.image?lk3s=5b7047ff&x-expires=1784835799&x-signature=KQpLHlEBY1LQhUagCZOePkbhxp4%3D",
        "url": "https://fanqienovel.com/page/7648703156582353982"
      },
      {
        "title": "觉醒异能，我把自己上交国家",
        "author": "独狼玩家",
        "reads": "10.1万",
        "intro": "［异能］+［爽文］+［抱国家大腿］+［不降智］+［杀戮果断］ 凌晨两点，林晨凭空凝出一团橘红色火焰。 当全网都在幻想觉醒异能后称霸世界，唯有他第一时间冲进派出所：“警察叔叔，我觉醒超能力了，我要上交国家！” 这份赤诚滚烫，国家从未半分亏待，更做了他最坚实的靠山，举国顶尖资源向他全力倾斜，林晨只管放手前行。 身前守国土防线，身后有国家撑腰，谁敢越雷池半步，自有国法与铁拳替他兜底。 三个月后，国家异能管理局正式成立。 林晨肩扛少校军衔，手握华夏第一异能战队指挥权。 赤焰所及之地，便是国土防线；火光所向之处，尽是家国安宁！ 当全球异能时代悄然降临，世人惊觉： 东方的第一缕火种，早已燃成燎原之势！",
        "cover": "https://p3-reading-sign.fqnovelpic.com/novel-pic/p2o37b0f4fa66d12851fd330a22dd3c1d60~tplv-resize:225:0.image?lk3s=5b7047ff&x-expires=1784835799&x-signature=bvTb%2F5VvGQR2OU%2B5DQTumvulvWg%3D",
        "url": "https://fanqienovel.com/page/7647532185674599486"
      },
      {
        "title": "国运拼哥：我大帝修为被妹妹曝光",
        "author": "军爷爱上大东北",
        "reads": "9.4万",
        "intro": "【国运拼兄直播系统】降临蓝星，全球每个国家随机抽取一名妹妹进入禁地！ 别国妹妹拼的哥哥：特种兵、科学家、财阀大佬…… 龙国妹妹苏若若拼的哥哥：三年前车祸去世的辍学打工仔？ “叮！检测到龙国天选者哥哥苏玄身份异常，开始曝光修仙界生平！” 画面一出，全球沸腾了！ 从最底层杂役，到历经三万年血战，踏着亿万天骄尸骨登临帝座！ 【震惊值+9999！】 【龙国具现奖励：极品灵脉一条，全民寿元+100年！】 别国哥哥还在秀肌肉，苏玄直接隔空一剑斩碎星辰！ 看着被吓尿的各国选手，苏若若呆住了…… “哥，你不是死了三年吗？怎么打成无上大帝了？！” 伴随无数榜单曝光，各国天选者和全球观众都懵逼了。 “我哥的榜一宠物叫吞天魔龙？” “我哥的榜一武器叫极道帝兵？” “第哥的榜一宗门叫天庭？仙王叩首？” “我哥他……还经历过百国大战、三千宗天才大战、镇压九域黑暗动乱、最后还！！独断万古！！” “哥！咱们真牛逼！” “什么叫我那死去的哥哥携极道帝兵升空了！”",
        "cover": "https://p3-reading-sign.fqnovelpic.com/novel-pic/p2o99266ccbf72023064c8f63d88375573b~tplv-resize:225:0.image?lk3s=5b7047ff&x-expires=1784835799&x-signature=Wv1uvrG%2FxYHHch7cDCWZWBG8rK4%3D",
        "url": "https://fanqienovel.com/page/7647113347116059672"
      }
    ]
  },
  "categories": [
    {
      "name": "都市高武",
      "trend": {
        "new_count": 4,
        "dropped_count": 4,
        "new_books": [
          "高武：我岩王帝君，专治各种不服",
          "我开启的宝箱品质永远加3",
          "觉醒异能，我把自己上交国家",
          "国运拼哥：我大帝修为被妹妹曝光"
        ],
        "dropped_books": [
          {
            "title": "天幕让你当废物班长你独断万古？",
            "intro": "【新题材+全网首发+群像+爽+甜+全员老六】 【评分刚出后续会涨，请放心食用。】 叶楚昊穿越至异界，历经亿万年修成无敌仙帝，无聊之下回归原点，成了全国公认最差班级，高三（9）班的废柴班长。 　　本想收"
          },
          {
            "title": "全球异能：开局觉醒七大原罪分身",
            "intro": "评分刚出，后面会...算了涨不涨我也不知道，先看再说！ 【灵气复苏】【杀伐果断】【不圣母】【腹黑】【分身】 这是人族最为璀璨的时代，人族立于万界之颠，所有世界，都是猎场，也是资源！ 林白穿越而来，本以"
          },
          {
            "title": "我一正经邪神，只接受合法献祭",
            "intro": "（评分刚出+无敌流+大一新生+乐子仙人+高调之神+三清列仙出没） 【肌肉男】【社畜】【大明星】【零】 某天，大一新生陈川发现，人们头上出现一个个这样的词条。 而他，可以自由买卖这些词条。 或者说是，献"
          },
          {
            "title": "觉醒序列孙大圣，二郎学姐太撩了",
            "intro": "【剧情流】+【非无脑爽】+【神话序列】 霓虹与钢铁的阴影里，他们的厮杀从未停止。 　　在这座城市的背面，怪物们伪装成人，以血肉为食；天幕的深处，旧神们垂下眼眸，冷眼旁观。 　　灾域与现世的交错中，哪一"
          }
        ],
        "top_risers": [
          {
            "title": "造化工厂：保卫科个个是神魔！",
            "change": "+4"
          },
          {
            "title": "契约不了机娘？内燃机了解一下",
            "change": "+3"
          },
          {
            "title": "国术：从被武警搜山击毙开始见神",
            "change": "+1"
          }
        ],
        "top_fallers": [
          {
            "title": "假面骑士的我，还是抱错的真少爷",
            "change": "-2"
          },
          {
            "title": "异兽入侵：我编造了铠甲救世组织",
            "change": "-2"
          },
          {
            "title": "我才三岁，怎么会是灭世级灾厄",
            "change": "-1"
          }
        ],
        "reads_growth": [
          {
            "title": "第一次破译免费？反手破译系统！",
            "growth": "+1.0万"
          },
          {
            "title": "我都宇宙之主了，你们还在地球？",
            "growth": "+9000"
          },
          {
            "title": "国术：从被武警搜山击毙开始见神",
            "growth": "+6000"
          }
        ],
        "summary": "**🔥 题材趋势**  \n「国运直播+系统金手指」仍是绝对主流（《国运拼哥》《第一次破译免费》等7本），「修仙与高武融合」扎堆（晚年大帝、岩王帝君、真少爷修仙），「无敌流+情绪爽点」成为"
      },
      "books": [
        {
          "title": "我都宇宙之主了，你们还在地球？",
          "author": "吒牛",
          "reads": "37.9万",
          "intro": "徐缺觉醒了金手指，获得了天赋抽取能力！ 天赋一：【长生不老】每天增加1年寿命，无上限。 天赋二：【逆天悟性】每天增加1点悟性，无上限。 天赋三：【百倍暴击】每天修炼进度百倍暴击！ 天赋四：【你的命就是我的命】每斩杀一人，获得一条命，无上限。 天赋五：【我自带泉水】每秒恢复1%的任何伤势。 天赋六：【一念诸天】自由往来无数位面。 天赋七：…… ………… 【姓名：徐缺】 【代号：混沌】 【档案密级：绝密】 【危险等级：SSS（？？？）】 【目标常态：外表为普通青年男性，无明显超凡特征，日常行为模式与常人无异】 【已观测能力清单（不完全统计）】 【1：具体实力不详，但肉体横渡虚空，硬扛核弹，无视一切现有科技】 【2：X年 X月，第一头SSS级妖皇复苏，高62米，长116米，片刻后，这头巨兽疑似被目标击杀，举世哗然！】 【3：X年X月，数十头超越妖皇的存在复苏，末日降临……】 【4：……】 【998：该死！他自杀了？不对，他怎么又活了？】 【999：他居然是不死的！】 【警告：目标极其危险，极其危险，极其危险，不可贸然接触，接触极易触发不可控后果！】 【建议：全面监控，严禁一切形式的主动接触，所有主动接触者，以叛国罪，反人类罪论处！】",
          "cover": "https://p3-reading-sign.fqnovelpic.com/novel-pic/p2o96c2eeca26d8cbcc3fd8f54f7cd3ae5f~tplv-resize:225:0.image?lk3s=5b7047ff&x-expires=1784835795&x-signature=xHLlaNsfTPIVL73JjvgwduQuOCo%3D",
          "url": "https://fanqienovel.com/page/7644040936980220953"
        },
        {
          "title": "第一次破译免费？反手破译系统！",
          "author": "我不吃牛肉c",
          "reads": "37.5万",
          "intro": "【诸天妖孽大舞台、卡bug、乐子文、癫】 宇宙升维考验开始，所有文明的智慧生物都要参与此次试炼，创造出打破这方宇宙极限的修炼体系… 蓝星也从此进入了全新时代。 林挽成为了第一批试炼者，每一次试炼，都将与整个宇宙所有智慧生命同台竞技。 他脑海多了个破译系统，可选择天地万物进行破译，破译后可获得其本源代码。 资源可实现量产！ 天赋、资质、修行感悟亦可取而代之！ 可破译需要破译点，破译点需要击杀智慧生命才能获得。 但是，第一次破译免费，无需消耗破译点。 林挽反手将第一次破译次数用来破译破译系统。 然后他系统直接乱码了。 【破译点：#@%¥】",
          "cover": "https://p3-reading-sign.fqnovelpic.com/novel-pic/p2oc07b0958d47f4b0d90fc6893dc4d45bb~tplv-resize:225:0.image?lk3s=5b7047ff&x-expires=1784835795&x-signature=8huMOwRA7jGnNNbqPnQ6J7b4xug%3D",
          "url": "https://fanqienovel.com/page/7633400795525811262"
        },
        {
          "title": "国运：沉睡棺中，八大阴将守华夏",
          "author": "浮云的云",
          "reads": "26万",
          "intro": "【国运+直播+阴门八将+师徒传承+爽文+群像】 国运游戏降临，全球各国随机选出九人守护国门。 华夏这边，八个\"守村人\"和一口漆黑棺材被传送进国运空间。 全网炸了！ \"完了！八个智障加一口破棺材，华夏要亡！\" \"其他国家都是特种兵、异能者，我们这是什么鬼阵容？\" \"建议直接投降，别浪费时间了……\" 然而，当第一波怪物攻城时—— 捞尸人一根竹竿，尸潮倒卷； 缝尸匠飞针走线，缝合怪物成傀儡； 赶尸匠铃铛一响，万鬼听令； 扎纸匠剪刀翻飞，纸人化军团； 棺材匠一锤定音,怪物当场暴毙； 唢呐匠一曲《百鸟朝凤》，送敌人上西天； 风水先生罗盘一转，改天换地； 刽子手鬼头刀出鞘，斩尽一切不详！ 全球震惊：\"这就是华夏的'智障'？\" 而那口黑棺中，沉睡着他们共同的师傅—— 阴门之主，苏晨。 \"徒儿们，为师先睡了，等华夏国运昌盛之日，便是为师出棺之时。\" \"在那之前，这国门……你们守得住吗？\" 八大阴将齐声：\"师傅放心，有我们在，华夏国门，固若金汤！\"",
          "cover": "https://p3-reading-sign.fqnovelpic.com/novel-pic/p2o52ce5b6ddb269f3f9c10a8d2a15890b4~tplv-resize:225:0.image?lk3s=5b7047ff&x-expires=1784835795&x-signature=uM5dtgE3OmonZfXu3XnyuN2N53I%3D",
          "url": "https://fanqienovel.com/page/7651928955489897534"
        },
        {
          "title": "晚年大帝，被妹妹召唤国运求生？",
          "author": "七十岁殿堂之资",
          "reads": "16.8万",
          "intro": "【国运求生+直播+诡异入侵+晚年大帝】 陆离穿越玄天界，帝路争锋，成为永夜魔帝。 万年后，举世皆寂，故人凋零，而他也步入了晚年。 这一日，他却听到了来自蓝星的血脉至亲，妹妹陆雪瑶的呼唤。 …… 龙国，749局觉醒仪式上，陆雪瑶召唤出哥哥陆离的投影，成为自己的本命诡宠。 这一日，国运游戏降临，每个国家随机挑选两个天选者，进入诡异世界求生。 只要在诡异世界中建立领地，就能抵挡诡异源头入侵现实世界。 选手死亡，将扣除本国国运，降临惩罚，选手在国运游戏中获得的资源，将有概率暴击返还给所在国家。 当其他天选者饥寒交迫，还在与诡异对抗，艰难求生时。 陆雪瑶在哥哥的指导下，已经在诡异世界中建立了无上魔国，万诡俯首，八方来朝。",
          "cover": "https://p3-reading-sign.fqnovelpic.com/novel-pic/p2o86548e72ba089a13387b0df3d6812494~tplv-resize:225:0.image?lk3s=5b7047ff&x-expires=1784835795&x-signature=q%2BiJqftBFoIAsmaeohiOBhjBNmI%3D",
          "url": "https://fanqienovel.com/page/7652308382908419096"
        },
        {
          "title": "国术：从被武警搜山击毙开始见神",
          "author": "四夕刂",
          "reads": "21.9万",
          "intro": "评分低是因为新书【龙蛇流】+【国术】+【民国】+【无系统】+【天才流】 陈洪武遭人陷害入狱三年，得奇人传授国术，出狱后明劲大成，却突闻噩耗—— 父母为自己奔走上诉劳碌而死！ 陈洪武怒上梁山，狂徒磨刀，管你权贵还是差人，皆要命丧拳下！ 咫尺之内，人尽敌国！ 挑战法律红线的陈洪武最终被武警部队击毙。 一朝醒来，却发现自己成了民国富少爷。 军阀割据、列强环伺！ 国术式微、妖魅魍魉横行！ 陈洪武重走武道之路，凭借铮铮铁拳，打出个煌煌大世！ 明劲、暗劲、化劲、丹劲、罡劲、金刚不坏、见神… 当陈洪武念头一动，滚滚天雷落下，面前钢铁巨舰化作铁水。 世人惊呼：这还是国术？",
          "cover": "https://p3-reading-sign.fqnovelpic.com/novel-pic/p2of3ec01a79dc5237e0b70cd764b83c1f6~tplv-resize:225:0.image?lk3s=5b7047ff&x-expires=1784835795&x-signature=fVnwLmQRRntHHIVkdGjHftHymbw%3D",
          "url": "https://fanqienovel.com/page/7647892624631680025"
        },
        {
          "title": "我才三岁，怎么会是灭世级灾厄",
          "author": "少喝冰镇饮料",
          "reads": "15.9万",
          "intro": "三年前，江洛穿越来到这个世界，成为一名刚出生的婴儿，并觉醒了【属性系统】。 系统告知他，这个世界很危险，但只要每存活一天，就能得到一个属性点。 江洛信了，小心翼翼活到了百日宴后，才发现这世界跟他前世的蓝星世界一模一样，从历史文化到科技发展，甚至时间线都没变，半点危险都看不到。 这让江洛以为，这有可能是个错位系统。 然而，当他两岁时的一次人前显圣失败后，他才发现，这系统根本屁用没有！ 就当江洛以为，这一生会平平淡淡的过下去时，一场突如其来的凶险，打碎他的安逸生活…… …… “灾厄？超凡者？诡异？凶兽？” “我去，狗系统你居然是对的？” 江洛彻底懵了。",
          "cover": "https://p3-reading-sign.fqnovelpic.com/novel-pic/p2oa421dbf8d89fa1129fc35612736958df~tplv-resize:225:0.image?lk3s=5b7047ff&x-expires=1784835795&x-signature=a8UPf3wYQVVtxeG%2Br7F%2Bd1OHUt0%3D",
          "url": "https://fanqienovel.com/page/7639494219232463897"
        },
        {
          "title": "本体SSS级，镜像也是SSS级",
          "author": "颜尽欢欢",
          "reads": "14.3万",
          "intro": "评分刚出！！！【SSS镜+单女主+无敌+快节奏+情绪路径】 　　 　　序列觉醒日，薄烬觉醒【梦魇】路径，世界上唯一的SSS级序列【镜】。 　　 　　技能包括但不限于：破镜之刃，折射，破碎，空间，武装。 　　 　　【镜中世界：倒映出一个初始面积为100平米的镜中世界，每一次升阶都可以提升镜的面积。】 　　 　　【双镜：映照出一个与本体一模一样的镜像，镜像与本体都是SSS级，且可以使用所有技能！】 　　 　　所有的序列者天才都震惊了。 　　 　　“这不是挂？！” 　　 　　“一个SSS级就已经很超标了，你居然有两个？！” 　 　　若干年后，堕落者攻陷了整个世界。 　　 　　“哈哈哈！” 　　 　　“序列者路边一条！” 　　 　　这时。 　　 　　一只遮天蔽日的手掌覆盖而来，整个世界变得一片黑暗。 　　“镜中世界！” 　　天外，或者说镜外。 　　 　　薄烬看着手中的镜面，其内倒映出无数堕落者所在的整个世界。 　　 　　下一刻。 　　 　　他手指轻轻一点。 　　 　　咔嚓。 　　 　　镜面破碎。 　　 　　整个世界也在这清澈的声响中随之破碎毁灭。",
          "cover": "https://p3-reading-sign.fqnovelpic.com/novel-pic/p2odc46ade11f117c5230b3f23454f1a4bd~tplv-resize:225:0.image?lk3s=5b7047ff&x-expires=1784835795&x-signature=hCFJAo48ZjvAGL8vqjZb28HuQSc%3D",
          "url": "https://fanqienovel.com/page/7650374971725728792"
        },
        {
          "title": "全民神祇时代：我的词条每日刷新",
          "author": "些许风霜过去",
          "reads": "17万",
          "intro": "陆胜穿越到了一个人人皆可成为神明，掌控法则，开辟小世界的超级世界。 主世界一天，小世界一年。 陆胜开局觉醒C级天赋词条【繁育之乡】，小世界内还有B级建筑【灵眼之泉】，妥妥的小天才一枚。 但没有人知道的是，陆胜还有一个X级天赋【词条之主】 主世界每天零点时间，他的小世界就会准时刷出一个新的词条！ 并且，以前拥有的词条不会消失！ 直到【融合】的词条出现，陆胜开始把拥有的词条一一融合…… C级【繁育之乡】+B级【多子多福】=S级资源词条【丰饶之巢】 D级【兽血沸腾】+A级【先天灵体】=SS级血脉词条【荒古灵兽身】 S级【演化加速】+A级【万物生长】=SSS级推演词条【时间掌握】 别人终其一生都只能获得一个天赋词条，而在陆胜这里，顶级词条随便批发！ ………… 【记载】：您的小世界灵气浓度提升百倍，子民修炼速度加快，高级资源出现的概率更高！ 【记载】：您的子民中已出现圣人级生物！ 【记载】：您已经攻破超大型神国，请尽快占领该世界，掠夺资源！ 当同龄人还在考虑省来的信仰点去买什么资源卡比较好，怎么培养自己的子民时—— 陆胜的小世界内已经人人成圣，建立仙朝，反攻异族神明了",
          "cover": "https://p3-reading-sign.fqnovelpic.com/novel-pic/p2oe4aa10d5cf17de514cb635315e38fef9~tplv-resize:225:0.image?lk3s=5b7047ff&x-expires=1784835795&x-signature=%2F7L%2Bn1t2Z%2BlNm67RFPPHPjo1LUM%3D",
          "url": "https://fanqienovel.com/page/7644794897249094718"
        },
        {
          "title": "变身：开局召唤铁幕，一击灭国运",
          "author": "螃蟹9527",
          "reads": "17.4万",
          "intro": "【前期国运+中期诸天万界+直播+性转+变身+变百+无敌+爽文+铁墓+崩铁……】 国运游戏入侵。 「苏亦晓选手运气爆棚！三枪打碎异族魂！」 「传奇狙击手苏亦晓还在猎杀！」 「天呐！苏亦晓选手转起来了！墙壁在开枪！墙壁在开枪！」 “别人都在老老实实攀科技，我直接转起来全秒了，就很，你懂吧？” …… 铁墓降临！ 高级文明：区区绝灭大君，我等必将令其燃烧！ 高级文明：？我家成矿了？ 顶级文明：区区铁墓，我等必将令其毁灭！ 顶级文明：？我家跌入混沌了？ 神级文明：这是不可跨越的鸿沟！毁灭于此！ 神级文明：？什么叫，你给我家锁了？ “别人都在老老实实玩国运游戏，就我来个铁墓给国运游戏炸了，就很，你懂吧？” …… 诸天万界。 天幻论道游戏。 别人：吾之剑道！无往不利！ 别人2：魔法！是我指尖跃动的信仰！ 别人3：科技至上！ 别人4：武道无穷！ 然后我：白昼与黑夜相等吗？义人与罪人相等吗？ 就很…… …… （后续包括但不限于黄金裔，星核猎手，幻胧，归寂，星啸，卡卡目，浮黎涟等等）",
          "cover": "https://p3-reading-sign.fqnovelpic.com/novel-pic/p2ob5a91611659882a2e4b1c2184499c012~tplv-resize:225:0.image?lk3s=5b7047ff&x-expires=1784835795&x-signature=a9%2BJpTjH0dXpbKYLI5Fw%2BpVWPqI%3D",
          "url": "https://fanqienovel.com/page/7652991563122887705"
        },
        {
          "title": "杀一怪叠一毒，我一人毒穿世界！",
          "author": "风样男子",
          "reads": "11.9万",
          "intro": "（评分刚出，后面会涨） 【全民+无限成长+无敌+稳重主角+爽爽爽】 游戏降临现实，全民转职时代开启。 　　苏尘觉醒了SSS级唯一隐藏职业——剧毒法师。 　　在这个别人下副本要死要活，面对高防高血Boss只能疯狂刮痧的时代，苏尘看着自己的职业特性陷入了沉思。 　　【特性1：你的任何攻击，强制为目标施加无法驱散的剧毒，每秒造成高额真实伤害。】 　　【特性2：你的毒素层数可无限叠加，每杀1个怪，上限+1。】 　　于是，画风变了。 　　别人眼里的毒法：刮痧、脆皮、没爆发。 苏尘眼里的毒法：卡机制、挂真伤、无限折磨！ 　　当其他天才还在为了一个首杀拼死拼活时。 　　苏尘只是对着深渊级BOSS平A了一下，然后转身找了个安全的地方坐下，开始悠闲地吃便当。 　　“别洗了，这debuff你洗不掉的。” 　　“血条长？那就多折磨你一会。” 　　多年后，当异界邪神降临，看着自己身上那几百万层无法驱散的剧毒，破防了：“这个毒系，怎么这么恶心啊？！” 　　苏尘无奈摊手：“我只是平A了一下，怎么全疯了？”",
          "cover": "https://p3-reading-sign.fqnovelpic.com/novel-pic/p2o74c49a7674387bb963be2790d7b935bf~tplv-resize:225:0.image?lk3s=5b7047ff&x-expires=1784835795&x-signature=2RvvmDjBmJXAEM9jd%2Bo98aDAjWY%3D",
          "url": "https://fanqienovel.com/page/7650816869128997912"
        },
        {
          "title": "黑暗拍卖会，开局拍下反派萝莉！",
          "author": "我吃姜丝",
          "reads": "8.4万",
          "intro": "【都市高武】【修仙】【反派】【轻松向】【多女主】【偏日常】 自从穿越而来，姜川一直以为自己过的是悠闲大少的日常生活，但万万没想到，老祖一出关就干死了八大家族。 姜川：“啊？原来我是反派命格吗？” 洛浅浅：“不，你不是反派！我才是！”",
          "cover": "https://p3-reading-sign.fqnovelpic.com/novel-pic/p2o0d953b5dc46da02aed9774a263db510c~tplv-resize:225:0.image?lk3s=5b7047ff&x-expires=1784835799&x-signature=Xz2TWDRTXzR%2B632ZSbnKg0Z9mm4%3D",
          "url": "https://fanqienovel.com/page/7649403749978344510"
        },
        {
          "title": "高武：不好了！真少爷是个修仙的",
          "author": "道友乱谈琴",
          "reads": "12.2万",
          "intro": "【评分刚出，后面会涨】 【全民高武我修仙，我笑别人看不穿】 林燃撞大运穿越到一个灵气复苏的高武世界，成了一个没能觉醒天赋的普通高中生。 并且，正在遭受一场围殴。 在这个强者为尊的世界，他一个没权没势，还没有天赋的孤儿，遭到欺凌似乎也很正常。 就当他快要被人打死的时候，发现了识海中的异常。 前世购买的一只青铜小鼎竟然随他穿越而来。 而此时，青铜小鼎之上正浮现出一部功法。 《万宝铸灵诀》，一部可以让没有灵根的人踏入仙途的逆天功法。 但是这功法每提升一个大境界，就需要炼化一件宝物。 好在识海中的青铜小鼎本身就是一件宝物，能够让他成功迈入炼气期。 借助青铜小鼎修复了伤势的林燃，趁势反击，将几名围殴他的人暴揍一顿。 原本应该算是正当防卫的他，又遭到保安的为难。 不出意外的话，意外出现了。 一对夫妇找到了他，并声称是他的亲生父母。 眨眼间，他又成了豪门流落在外的少爷。 前世操劳半生，也没享过什么福。 如今给他一个当少爷的机会，他却觉得索然无味。 都修仙了，谁还稀罕当什么豪门少爷？ “燃儿，我是你的亲生母亲啊！” “抱歉，这位女士，我们不熟。所以还是请你不要这样称呼我，那会让我觉得很不自在。”",
          "cover": "https://p3-reading-sign.fqnovelpic.com/novel-pic/p2o35a4a8690d00153ce01289cf8c0d74c3~tplv-resize:225:0.image?lk3s=5b7047ff&x-expires=1784835799&x-signature=EC5GMbMQ71lJ2G0WtN5mQ5esuxs%3D",
          "url": "https://fanqienovel.com/page/7645554869385825304"
        },
        {
          "title": "假面骑士的我，还是抱错的真少爷",
          "author": "我是快乐的人机",
          "reads": "8.4万",
          "intro": "【假面骑士+真少爷与结巴假千金+有骑士精神】（前面有一个穿越者小反派不过剧情不多不喜误进） 别人穿越，开局自带金手指系统。叶阳穿越，开局自带一台品红相机。上一世，叶阳的世界被怪兽入侵，命悬一线之际，帝骑和空我从天而降把他救了下来。事后所有人都说他是看特摄看魔怔了，差点把他送进精神病院。只有叶阳知道，自己作为全世界唯一记得真相的人，肯定摊上大事了。果然，转头就被一辆大运创飞。被创飞的一瞬间，他来到了一个白茫茫的空间，面前站着的正是那位路过的假面骑士。帝骑把同款品红相机递过来，并说道：骚年，你的旅途开始了。 而叶阳只来得及喊出一句：“你千万不要想不开去拍什么时王外传啊！会变成池塘守护者的！！”然后他就穿越了。新的人生，依旧被抱错，依旧孤儿院，依旧天崩开局。叶阳只想问帝骑哥一句：你穿越给我穿越好啊，倒是给我穿个好点的人家啊？ 结果事情越来越离谱—— 什么？我是林家大佬唯一的儿子？ 什么？我上面还有三个姐姐？ 什么？那个跟我抱错的假千金，居然是我网上聊了好几年的网友哥们？！ 叶阳举起相机，拍下了自己目瞪口呆的脸。 品红相机记录世界，而他负责在这操蛋又离谱的人生里，找到所有值得按下快门的瞬间。",
          "cover": "https://p3-reading-sign.fqnovelpic.com/novel-pic/p2o4fc35c26aeb89f641a6c7c1d7eaf6be3~tplv-resize:225:0.image?lk3s=5b7047ff&x-expires=1784835799&x-signature=y1Az%2BS%2BZr1%2B2aI5yZNvoTQWUizw%3D",
          "url": "https://fanqienovel.com/page/7652299898301205528"
        },
        {
          "title": "契约不了机娘？内燃机了解一下",
          "author": "飞雷神千鸟流",
          "reads": "11万",
          "intro": "【女主牢妹】【赛车竞技】【内燃机VS赛车机娘】 齐星开局被全险半挂做局，一代电竞天才少年就此陨落，穿越到文娱落后的机娘纪元世界，可重来一世还是造化弄人，大四的觉醒仪式上觉醒SSS级天赋却不能契约机娘？ “来小家伙，接受姐姐的怀抱吧” 齐星被S级机娘纪云棠看上，然而就在他与纪云棠连接精神链接的时候： 【检测到风险程序入侵，第三方强制契约失败！】 “无视风险继续安装！”齐星下意识脱口而出。 【安装失败，退出安装并删除！】。 齐星不死心接受契约失败的结果，接连与其他等级的机娘短暂邂逅，无一例外全是第三方强制契约失败，让他沦为全校的笑柄。 齐星：你说这扯不扯？先跳了，兄弟！ 就在他心灰意冷之下，被一个系统找上门，他可以在系统商城内够买前世所有类型的内燃机。 “系统，内燃机怎么跑得赢机娘？” 【科学的尽头是烧开水，武力的尽头是丢石子，如果机娘冒黑烟，那证明她已经到达了极限，而内燃机冒黑烟，说明它才刚刚发力。】 【你问内燃机凭什么赢？】 【因为钢铁不需要“爱”来驱动……】 【它只需要更粗的涡轮！更硬的凸轮轴！以及……】 【更多不怕死的疯子！】 【宿主，只要有钱，什么牛鬼蛇神都能买到。】",
          "cover": "https://p3-reading-sign.fqnovelpic.com/novel-pic/p2o3ff61f663a6f974f082704c5b865cd88~tplv-resize:225:0.image?lk3s=5b7047ff&x-expires=1784835799&x-signature=u0jPFgTSdeWpYSsOCDvahRGHyD8%3D",
          "url": "https://fanqienovel.com/page/7652027487576132632"
        },
        {
          "title": "造化工厂：保卫科个个是神魔！",
          "author": "大侠爱吃土豆",
          "reads": "10万",
          "intro": "林玄穿越高武世界，觉醒造化工厂系统，任何物品都可以被造化工厂解析，随后用最基础的材料制造出来。 “解析培灵丹，解析完成，持续输入灵气即可炼制！” 于是乎，林玄招募一万聚灵境底层人民，三班倒，日夜不停地在流水线输送灵气，源源不断的培灵丹被批量生产出来。 别的供货商卖三万联邦币一颗，林玄只卖三千！ “解析三品武器纳米战甲！解析完成，持续投入一品黑铁矿和聚灵境妖兽肉即可炼制。” 林玄反手又招募十万员工，开始日夜不停地炼制纳米战甲。 百宝阁卖上亿联邦币，林玄只卖一千万！ 百宝阁阁主脸色难看：“该死，这家伙炼制丹药武器不要成本的吗！？” “找人，弄死他！” “阁主，不好了！造化工厂的数十万工人暴动了，说咱们要是敢动林玄一根汗毛，他们就要灭了百宝阁！” “阁主，不好了！林玄说要搬走去其他城市，城首下令，三天之内咱们必须道歉，否则就要提供百万岗位承接造化工厂的工人。” “阁主，不好了！造化工厂的保卫科出动了，个个都是神魔，说是要在走之前把碍眼东西清理掉！” ………",
          "cover": "https://p3-reading-sign.fqnovelpic.com/novel-pic/p2o27dc0267604306732b0feba177deb045~tplv-resize:225:0.image?lk3s=5b7047ff&x-expires=1784835799&x-signature=Y6yPv%2BoNlqDWlZPR%2B5OwOCHaJZo%3D",
          "url": "https://fanqienovel.com/page/7647538764155210776"
        },
        {
          "title": "高武：我岩王帝君，专治各种不服",
          "author": "羽风无痕",
          "reads": "11.2万",
          "intro": "【每日10点更新，请大家准时期待！】 【评分刚出还有些低，看到我的在新书榜前30就知道不错了，值得入坑。】 这是一个异能觉醒的时代，虚空裂缝横跨苍穹，无数诡异生物降临人间。 林长歌穿越而来，在觉醒仪式上，意外加载了【岩王帝君·摩拉克斯】人物模板。 世人皆以为岩系异能只是平庸的防御，却不知林长歌眼中的世界早已不同。 “契约已成，食言者当受食岩之罚。” 他行走在城市边缘，随手一挥，玉璋护盾笼罩全城，任凭千万异兽轰炸，我自安如磐石。 当神级虚空之敌撕裂空间，人类防线全线溃败之际。 林长歌踏空而行，长枪划破长夜，双瞳闪烁着金色的神芒： “天动万象！” 那一夜，一颗千米陨石从高维坠落，将方圆百里化为石林，神明陨落！",
          "cover": "https://p3-reading-sign.fqnovelpic.com/novel-pic/p2o96e3506df38dae2021b109688a65b68b~tplv-resize:225:0.image?lk3s=5b7047ff&x-expires=1784835799&x-signature=TEJ08NLx6xin6KePclC2tpUUs50%3D",
          "url": "https://fanqienovel.com/page/7650143802287459352"
        },
        {
          "title": "我开启的宝箱品质永远加3",
          "author": "冒冒",
          "reads": "11.5万",
          "intro": "80多年前，超星游戏与现实融合，大量怪物冲击之下，人类只能建起高墙以阻挡怪物的入侵，幸好，玩家可以从游戏中获得实力和装备，带入现实，这才堪堪挡住了怪物的入侵。 在这里，年满18岁后，学校会统一组织进行觉醒仪式，只要觉醒天赋，就可以进入游戏，成为玩家，获取强大的实力。 林远是个穿越者，他居然……觉醒了两个天赋！ S级天赋【盾山】，你的体质永久提升200%。 还有等级不详、从来没有出现过的天赋【宝箱王】，你开启的所有宝箱，品质永远+3，并且开出的物品会强制适配你的等级。 林远以为自己要腾飞的时候，校长却带着他的企业家弟弟出现，甩出一张支票，想要购买他的天赋，移植给他觉醒失败的侄子，还发出了死亡威胁……",
          "cover": "https://p3-reading-sign.fqnovelpic.com/novel-pic/ai/p2o148efe28d582fc148d14fada15df2f56~tplv-resize:225:0.image?lk3s=5b7047ff&x-expires=1784835799&x-signature=HTREZt0yeXuMD%2FqdOJFO8mTagUQ%3D",
          "url": "https://fanqienovel.com/page/7657772314297109566"
        },
        {
          "title": "异兽入侵：我编造了铠甲救世组织",
          "author": "麦当劳打野",
          "reads": "8.1万",
          "intro": "【铠甲超凡+组织打造+半幕后+创造铠甲+异兽末世+无女主】 末世将至，异兽入侵！ 人类文明岌岌可危，现有的军事力量全面入侵之下两个小时机会文明毁灭！ 幸而周扬身穿水蓝星，携带“铠甲成真系统”降临这个世界。 只要他编造铠甲组织相关的剧情、故事、人设，就能影响别人的情绪，产生的特殊情绪越多，就能具现更多铠甲宇宙的神奇存在。 随后，一个名为“希光”的铠甲救世组织从时光的长河中浮现，一道道伟岸的身影在长河中熠熠生辉。 异兽浩劫，千年一次！ 而如今，是五千年一次的大劫！ 周扬：“我是希光组织的创建者，也是所有召唤人的导师！” 消防队长之子兼召唤人段炎正义凛然道：“你一天是异兽，你这辈子都会是异兽！” 清冷女总裁楚清月：“比钱赚钱，我更愿意成为一名召唤人！” 绝症患者王雷：“出招吧，反正你们都得死！” 一年后，浩劫降临，异兽全面入侵。 周扬领着希光组织所有成员，拿出召唤器，齐声高喊：“铠甲合体！” 异兽之神被打得神体黯淡碎成一段段的：“一个小星球，哪来的宇宙级强者！”",
          "cover": "https://p3-reading-sign.fqnovelpic.com/novel-pic/p2of2e1474061da4ab2c59daa69b369e4f0~tplv-resize:225:0.image?lk3s=5b7047ff&x-expires=1784835799&x-signature=KQpLHlEBY1LQhUagCZOePkbhxp4%3D",
          "url": "https://fanqienovel.com/page/7648703156582353982"
        },
        {
          "title": "觉醒异能，我把自己上交国家",
          "author": "独狼玩家",
          "reads": "10.1万",
          "intro": "［异能］+［爽文］+［抱国家大腿］+［不降智］+［杀戮果断］ 凌晨两点，林晨凭空凝出一团橘红色火焰。 当全网都在幻想觉醒异能后称霸世界，唯有他第一时间冲进派出所：“警察叔叔，我觉醒超能力了，我要上交国家！” 这份赤诚滚烫，国家从未半分亏待，更做了他最坚实的靠山，举国顶尖资源向他全力倾斜，林晨只管放手前行。 身前守国土防线，身后有国家撑腰，谁敢越雷池半步，自有国法与铁拳替他兜底。 三个月后，国家异能管理局正式成立。 林晨肩扛少校军衔，手握华夏第一异能战队指挥权。 赤焰所及之地，便是国土防线；火光所向之处，尽是家国安宁！ 当全球异能时代悄然降临，世人惊觉： 东方的第一缕火种，早已燃成燎原之势！",
          "cover": "https://p3-reading-sign.fqnovelpic.com/novel-pic/p2o37b0f4fa66d12851fd330a22dd3c1d60~tplv-resize:225:0.image?lk3s=5b7047ff&x-expires=1784835799&x-signature=bvTb%2F5VvGQR2OU%2B5DQTumvulvWg%3D",
          "url": "https://fanqienovel.com/page/7647532185674599486"
        },
        {
          "title": "国运拼哥：我大帝修为被妹妹曝光",
          "author": "军爷爱上大东北",
          "reads": "9.4万",
          "intro": "【国运拼兄直播系统】降临蓝星，全球每个国家随机抽取一名妹妹进入禁地！ 别国妹妹拼的哥哥：特种兵、科学家、财阀大佬…… 龙国妹妹苏若若拼的哥哥：三年前车祸去世的辍学打工仔？ “叮！检测到龙国天选者哥哥苏玄身份异常，开始曝光修仙界生平！” 画面一出，全球沸腾了！ 从最底层杂役，到历经三万年血战，踏着亿万天骄尸骨登临帝座！ 【震惊值+9999！】 【龙国具现奖励：极品灵脉一条，全民寿元+100年！】 别国哥哥还在秀肌肉，苏玄直接隔空一剑斩碎星辰！ 看着被吓尿的各国选手，苏若若呆住了…… “哥，你不是死了三年吗？怎么打成无上大帝了？！” 伴随无数榜单曝光，各国天选者和全球观众都懵逼了。 “我哥的榜一宠物叫吞天魔龙？” “我哥的榜一武器叫极道帝兵？” “第哥的榜一宗门叫天庭？仙王叩首？” “我哥他……还经历过百国大战、三千宗天才大战、镇压九域黑暗动乱、最后还！！独断万古！！” “哥！咱们真牛逼！” “什么叫我那死去的哥哥携极道帝兵升空了！”",
          "cover": "https://p3-reading-sign.fqnovelpic.com/novel-pic/p2o99266ccbf72023064c8f63d88375573b~tplv-resize:225:0.image?lk3s=5b7047ff&x-expires=1784835799&x-signature=Wv1uvrG%2FxYHHch7cDCWZWBG8rK4%3D",
          "url": "https://fanqienovel.com/page/7647113347116059672"
        }
      ]
    }
  ]
}