{
  "date": "2026-07-10",
  "prev_date": "2026-07-09",
  "trends": {
    "西方奇幻": {
      "new_count": 1,
      "dropped_count": 1,
      "new_books": [
        "异人娘培养手册"
      ],
      "dropped_books": [
        {
          "title": "转生帝国皇子，开局成为第一实例",
          "intro": "（评分刚出，后面会涨） 【无敌+多女主+慢热+西幻+多种族+无系统+伪反派+多重身份+微克微恐】 穿越异世界，转生成为成为名叫“赛缪斯”的婴儿皇族，并获得“第一实例”的无敌之能。 本该是万人之上的皇族"
        }
      ],
      "top_risers": [
        {
          "title": "尘世巨蟒，开局便登神！",
          "change": "+6"
        },
        {
          "title": "退队后，她们化身病娇找上门来",
          "change": "+6"
        },
        {
          "title": "西幻不该这样的？",
          "change": "+2"
        }
      ],
      "top_fallers": [
        {
          "title": "躺平的我却招惹到病娇这档子事",
          "change": "-4"
        },
        {
          "title": "命运小姐的速通手册",
          "change": "-3"
        },
        {
          "title": "重生虫族主宰，开局同化精灵少女",
          "change": "-3"
        }
      ],
      "reads_growth": [
        {
          "title": "龙骑士先生，龙娘们在追杀你啊！",
          "growth": "+1.1万"
        },
        {
          "title": "西幻不该这样的？",
          "growth": "+1.1万"
        },
        {
          "title": "转生魔树小姐，不知为何成了魔王",
          "growth": "+2000"
        }
      ],
      "summary": "**🔥 题材趋势** 龙骑士与龙娘题材热度最高，占据榜单头部。“恶役领主”、“科学化魔法”等创新设定成为细分热点。传统西幻框架与“病娇”、“无敌流”等网文高热度元素结合紧密。\n**📖 读者偏好** 偏好带有“龙娘”、“多女主”、“修罗场”等恋爱元素的奇幻冒险故事。同时，侧重“杀伐果断”、“无敌流”、“领主种田”等强爽点设定的作品也具备强大的市场号召力。\n**🆕 新上榜作品** 《异人娘培养手册》结合“航海”、“血脉”与“炼金”元素，切入“异人娘”这一细分赛道，市场反响积极。\n**📉 掉出榜单** 《转生帝国皇子，开局成为第一实例》因题材同质化且缺乏独特记忆点，竞争力不足而被淘汰。\n**💡 值得关注** 《龙骑士：开局被自己的银龙反骑》虽在读量高但位于榜首，需观察其后续口碑和留存能否支撑其长期霸榜。"
    },
    "东方仙侠": {
      "new_count": 2,
      "dropped_count": 2,
      "new_books": [
        "从获取尸解法开始",
        "修仙：原来金手指全靠抢啊"
      ],
      "dropped_books": [
        {
          "title": "洪荒：仙杏化形，拜师元始",
          "intro": "穿越的风，终究是吹到了芥子舟！ 魂穿洪荒，成了昆仑山上的一株仙杏，还是极品先天灵根。 在他不懈的努力之下，成功化形，并拜三清之一的元始为师，成为阐教首徒。 既来之，则安之。 哪成想，芥子舟这三个字会响"
        },
        {
          "title": "洪荒：盘古妹妹五岁半",
          "intro": "“额的！额的！都是额的！” 盘青青，盘古亲妹，混沌青莲养了万古才醒。 五岁半，软萌护短，见啥要啥。 三清是她侄子，祖巫是她晚辈。 这天，她戳了戳不周山的大阵，放出一只猴子。 “以后你就叫孙悟空，跟着姑"
        }
      ],
      "top_risers": [
        {
          "title": "洪荒：执掌天地五德，拜入截教！",
          "change": "+6"
        },
        {
          "title": "变身小萝莉，我竟是天道傀儡？",
          "change": "+4"
        },
        {
          "title": "老婆大人，原来你没死啊",
          "change": "+4"
        }
      ],
      "top_fallers": [
        {
          "title": "洪荒：我为文祖，创神话儒道体系",
          "change": "-5"
        },
        {
          "title": "这！这是谁把杨婵放我府上的？",
          "change": "-2"
        },
        {
          "title": "洪荒：顽石证道",
          "change": "-2"
        }
      ],
      "reads_growth": [
        {
          "title": "这！这是谁把杨婵放我府上的？",
          "growth": "+3.1万"
        },
        {
          "title": "佛门金蝉子？不，我是通天首徒！",
          "growth": "+2.0万"
        },
        {
          "title": "被大货车送去修仙，直接为元婴期",
          "growth": "+9000"
        }
      ],
      "summary": "**🔥 题材趋势** “洪荒流”与“老祖/家族流”是当前最大热门，分别占据头部和中坚位置。将现代概念如“财神”、“阴阳师”融入仙侠的“新仙侠”风格作品开始涌现。\n**📖 读者偏好** 读者普遍寻求“杀伐果断”、“不圣母”的主角人设，同时对“家族种田”、“幕后流”等慢热、注重经营和策略的叙事有较高接受度。轻松日常与修罗场等元素穿插其中。\n**🆕 新上榜作品** 《从获取尸解法开始》以“尸解仙”、“聊斋风”的另类设定吸引眼球；《修仙：原来金手指全靠抢啊》则凭借“强冲突”、“不择手段”的极致人设快速上位。\n**📉 掉出榜单** 《洪荒：仙杏化形，拜师元始》和《洪荒：盘古妹妹五岁半》或因设定新颖度不足、爽点不够密集，被后续作品替代。\n**💡 值得关注** 《五百年结婴，我金手指总算苏醒了》的“大器晚成”和《这！这是谁把杨婵放我府上的？》的“人情世故”路线，显示出差异化叙事的潜力。"
    },
    "科幻末世": {
      "new_count": 1,
      "dropped_count": 1,
      "new_books": [
        "我的病娇触手娘对我愈发变态"
      ],
      "dropped_books": [
        {
          "title": "逼我退队？反手契约金色传说软妹",
          "intro": "【末日高武+契约流+退队打脸+软萌女主+杀伐果断】 末日游戏降临，韩棠用三个月，把五名菜鸡带成了基地顶尖强者。 分晶核当天，队长李婉晴把本该属于他的四百枚晶核，塞给了入队仅两天的青梅竹马。 三枚垃圾晶"
        }
      ],
      "top_risers": [
        {
          "title": "我是纯血人类，异形你们慌什么？",
          "change": "+4"
        },
        {
          "title": "沙漠求生：开局一棵沙棘树",
          "change": "+3"
        },
        {
          "title": "末世：我这复活术太不正经了！",
          "change": "+3"
        }
      ],
      "top_fallers": [
        {
          "title": "全民垂钓：开局百万倍SSS天赋",
          "change": "-4"
        },
        {
          "title": "别再求生了，我真没觉醒炉鼎天赋",
          "change": "-1"
        },
        {
          "title": "末世重生，成为核电站供能无限",
          "change": "-1"
        }
      ],
      "reads_growth": [
        {
          "title": "游戏入侵：每秒永久涨一点生命值",
          "growth": "+2000"
        },
        {
          "title": "列车求生，我开宝箱百倍暴击",
          "growth": "-6000"
        }
      ],
      "summary": "**🔥 题材趋势** “末日求生+系统/特殊天赋”是绝对主流，“全民穿越”、“列车/公路求生”等具体模式层出不穷。融合“基因”、“异能”、“科技种田”的元素持续火热，近期“触手娘”、“病娇”等元素开始渗透。\n**📖 读者偏好** 极度青睐“无敌流”、“绝对统治”和“杀伐果断”的爽感。同时，“无女主”的纯生存种田流，以及“宠妻”、“囤货”的温馨日常流也拥有稳定受众。\n**🆕 新上榜作品** 《我的病娇触手娘对我愈发变态》精准捕捉了“末世+异兽+病娇”的复合热点，提供了人外娘与末世生存结合的新鲜体验。\n**📉 掉出榜单** 《逼我退队？反手契约金色传说软妹》或因“退队打脸”核心模式与“软萌女主”的搭配在当前市场竞争中失去优势。\n**💡 值得关注** 《末世重生，成为核电站供能无限》的“重生+国家基建”设定，《全球冰封，我无限燃油》的“反套路公路狂飙”都极具创新性和潜力，值得持续追踪数据表现。"
    },
    "都市日常": {
      "new_count": 3,
      "dropped_count": 3,
      "new_books": [
        "病娇就能为所欲为？我偏要治治你",
        "寂寞的寻爱",
        "神级学霸，从横扫数理竞赛开始"
      ],
      "dropped_books": [
        {
          "title": "丈母娘改嫁要我家产做嫁妆，死吧",
          "intro": "白手起家的林君，将自己公司的30%股份放在妻子于荷名下，只为一份宠溺的承诺。但他没想到，这份信任成了岳母眼中的肥肉。 当岳母逼迫于荷将股份转作嫁妆，甚至试图让未婚夫的小奶狗接手控制公司时，向来温顺的于"
        },
        {
          "title": "泡了前女友姐姐，她竟是公司总裁",
          "intro": "【评分刚出+反差萌现任+颠婆前任+抢夫+微逗比】 分手时，柳如燕说：“能不能把我们以前相爱的视频删掉？” “作为补偿，这几年你给我花的钱，我都还给你。” 竟有这种好事？ 沈逸闪电般掏出了二维码。 收款"
        },
        {
          "title": "我就想躺平退休，咋还成了一把手",
          "intro": "我叫陈安，平安的安。在体制内摸爬滚打这些年，没练出青云直上的本事，反倒悟透了行稳致远的真理。别人削尖了脑袋往上爬，我偏慢悠悠走我的路——该扛的我不躲，该干的我不推，至于那些勾心斗角的烂摊子，就把它们全"
        }
      ],
      "top_risers": [
        {
          "title": "睡了姐姐闺蜜，竟是顶流魅魔校花",
          "change": "+5"
        },
        {
          "title": "说好保密发货，你给我发个真的？",
          "change": "+4"
        },
        {
          "title": "糟了！我的网恋对象竟是苗疆圣女",
          "change": "+1"
        }
      ],
      "top_fallers": [
        {
          "title": "在女多男少世界的生存指南",
          "change": "-6"
        },
        {
          "title": "囚谋，疯批古堡女王跨国宠夫",
          "change": "-3"
        },
        {
          "title": "我一心科研，你喊我反派纨绔？",
          "change": "-2"
        }
      ],
      "reads_growth": [
        {
          "title": "我崛起，我征服",
          "growth": "-1.0万"
        }
      ],
      "summary": "**🔥 题材趋势** 强反差、强人设的“禁忌关系”与“病娇”元素成为流量密码，如师生、网恋奔现、睡错人等设定高频出现，以高情绪冲击力吸引点击。传统官场、商战题材热度相对下滑，需融合反差才能突围。\n**📖 读者偏好** 读者偏好“恋爱日常+单女主+甜爽”的轻喜剧，对“病娇”、“先婚后爱”等极致人设的宠溺互动接受度高，追求阅读快感。纯现实向或虐心情节的市场空间收窄。\n**🆕 新上榜作品** 《病娇就能为所欲为？我偏要治治你》、《寂寞的寻爱》、《神级学霸，从横扫数理竞赛开始》。前两者延续了“病娇”和“情感关系”的高热度，后者则切入了“学霸/科研”这一细分赛道，展现出题材的扩张可能。\n**📉 掉出榜单** 掉榜作品如《丈母娘改嫁要我家产做嫁妆》《泡了前女友姐姐》等，多为现实向商战、狗血伦理或总裁文，在“日常+甜宠”的浪潮下缺乏新意，未能形成情绪爆点。\n**💡 值得关注** 《睡了姐姐闺蜜，竟是顶流魅魔校花》排名飙升，验证了“禁忌关系+高概念人设（魅魔）”的爆款潜力；《神级学霸》入榜表明，在恋爱日常的包裹下，可融入“硬核”元素以吸引更广泛的男性读者。"
    },
    "都市修真": {
      "new_count": 1,
      "dropped_count": 1,
      "new_books": [
        "乡村御兽美食，开局美女总裁续命"
      ],
      "dropped_books": [
        {
          "title": "傻子和留守村妇",
          "intro": "乡村神医x都市修仙x多女争艳x无敌爽文x杀伐果断x种田致富 王大炮被打傻后丢回村子，意外获得无敌传承，从此逆天改命，修神功、驱恶霸、治百病、搞经济，无所不能，带领村子的留守村妇们发家致富，走上人生巅峰"
        }
      ],
      "top_risers": [
        {
          "title": "灵气复苏？前世女帝老婆也复苏了",
          "change": "+7"
        },
        {
          "title": "路遇黄皮子讨封，封它当玉皇大帝",
          "change": "+3"
        },
        {
          "title": "灵气复苏，两天成为红尘仙",
          "change": "+3"
        }
      ],
      "top_fallers": [
        {
          "title": "灵气复苏：但系统提前两年来",
          "change": "-7"
        },
        {
          "title": "乡村神医，张凡的凤流生活",
          "change": "-3"
        },
        {
          "title": "山野隐仙",
          "change": "-2"
        }
      ],
      "reads_growth": [
        {
          "title": "桃花沟",
          "growth": "+1.8万"
        },
        {
          "title": "九叔：撒豆成兵？我这是草木道兵",
          "growth": "+1.5万"
        },
        {
          "title": "大炮来了，全村都慌了",
          "growth": "+1.0万"
        }
      ],
      "summary": "**🔥 题材趋势** “乡村+修真”模式已成主流，大量作品通过“傻/穷小子获得传承”的底层逆袭公式，融合种田、神医、致富元素，提供极致爽感。传统僵尸/九叔IP仍有生命力但需创新。\n**📖 读者偏好** 读者对“无敌流”、“爽文”、“打脸”有明确需求，偏好短平快的升级节奏和财富、势力的快速积累。对“多女主”接受度高，“乡村神医”是当前最成熟的爽文框架。\n**🆕 新上榜作品** 《乡村御兽美食，开局美女总裁续命》。该作品在“乡村+种田”基础上创新性地加入“御兽”元素，与“美食”、“种田”结合，打造差异化核心看点，符合市场求新求变的需求。\n**📉 掉出榜单** 《傻子和留守村妇》掉榜，说明单纯依赖“傻子+无敌”的模板已显疲态，需要更具体、更具吸引力的创新设定来支撑故事，如“御兽”或“美食”等高概念标签。\n**💡 值得关注** 《灵气复苏？前世女帝老婆也复苏了》排名大幅上升，证明“大世界观+多世转生”的设定能有效拉升中后期期待感，为同质化的乡村修真提供了一种跳出框架的升级思路。"
    },
    "都市高武": {
      "new_count": 2,
      "dropped_count": 2,
      "new_books": [
        "黑暗拍卖会，开局拍下反派萝莉！",
        "异兽入侵：我编造了铠甲救世组织"
      ],
      "dropped_books": [
        {
          "title": "无限复活，被院长姐姐上交国家",
          "intro": "【天赋+副本+上交国家+团宠+无限复活】 穿越到龙国的陆沉，觉醒生命掌控者。 凡是范围内被标记的友军，死后可恢复巅峰，不限次数。 同时，陆沉还发现一个隐藏属性，每复活一人，他的全属性+1。 上交国家后"
        },
        {
          "title": "变身：开局召唤铁幕，一击灭国运",
          "intro": "【前期国运+直播+性转+变身+变百+无敌+爽文+铁墓……】 国运游戏入侵。 人类大场连败两场。 第三场开局不利垫底。 异族窃取副本胜利果实，骑脸嘲讽。 “人类？那不是能一脚踢死的东西吗？” 异族高调嘲"
        }
      ],
      "top_risers": [
        {
          "title": "假面骑士的我，还是抱错的真少爷",
          "change": "+2"
        },
        {
          "title": "全球异能：开局觉醒七大原罪分身",
          "change": "+2"
        },
        {
          "title": "杀一怪叠一毒，我一人毒穿世界！",
          "change": "+2"
        }
      ],
      "top_fallers": [
        {
          "title": "全球奇物降临，只有我有探宝雷达",
          "change": "-3"
        },
        {
          "title": "重生烛龙，我成了最强学院守护兽",
          "change": "-1"
        },
        {
          "title": "我一正经邪神，只接受合法献祭",
          "change": "-1"
        }
      ],
      "reads_growth": [
        {
          "title": "全民神邸：神明来也照样强制繁殖",
          "growth": "-4000"
        }
      ],
      "summary": "**🔥 题材趋势** “国运/全球流”、“系统流”和“无敌流”三分天下，且多采用高概念设定（如SSS级、宇宙之主、灭世级灾厄）来快速建立卖点。同时，假面骑士、铠甲勇士等非传统元素正成为新的流量入口。\n**📖 读者偏好** 读者追求“开局即巅峰”或“快速崛起”的极致快感，“无敌”、“爽文”、“杀伐果断”是核心标签。对“破译”、“词条”、“镜像”等能提供新鲜感的系统设定有极高容忍度和探索欲。\n**🆕 新上榜作品** 《黑暗拍卖会，开局拍下反派萝莉！》和《异兽入侵：我编造了铠甲救世组织》。前者以“拍卖会+反派”开局制造悬念，后者则验证了“铠甲/特摄”这一垂类题材的破圈潜力。\n**📉 掉出榜单** 《无限复活》《变身：开局召唤铁幕》等掉榜，反映了在数据增长压力下，“无限复活”等传统设定或缺乏独特概念支撑的作品难以维持高热度，平台流量加速向“脑洞/高概念”作品集中。\n**💡 值得关注** 《假面骑士的我》排名上升，标志着二次元/特摄文化正强力渗透网文，为高武题材提供了新的创作方向。这类作品通过“情怀杀”与“高武体系”结合，能有效吸引特定圈层读者并形成破圈效应。"
    },
    "历史古代": {
      "new_count": 1,
      "dropped_count": 1,
      "new_books": [
        "亡国后，女诸侯们争着抢我"
      ],
      "dropped_books": [
        {
          "title": "冒名当县令，错把始皇当亲爹",
          "intro": "【父慈子孝+种田欢乐+冒名为官】 　　贾平安穿越大秦，偶遇坠崖而死的赴任县吏，于是冒名顶替。为保身份，他努力治理地方，将贫困县发展为世外桃源。本以为隐瞒的很好，以后也能加官进爵，却没想到原主的父亲竟要"
        }
      ],
      "top_risers": [
        {
          "title": "退婚我？倾城公主点我绝世驸马",
          "change": "+5"
        },
        {
          "title": "我姐夫是太子，你说太子叫李承乾",
          "change": "+1"
        },
        {
          "title": "冒姓科举：我在将军府假装真少爷",
          "change": "+1"
        }
      ],
      "top_fallers": [
        {
          "title": "开局镇守虎牢关，曹老板爱死我了",
          "change": "-4"
        },
        {
          "title": "三国：从颍川三浪到开国功勋",
          "change": "-3"
        },
        {
          "title": "家父高洋：当皇帝哪有不疯的！",
          "change": "-2"
        }
      ],
      "reads_growth": [
        {
          "title": "冒姓科举：我在将军府假装真少爷",
          "growth": "+1000"
        },
        {
          "title": "垂死病中惊坐起，袁绍竟是我自己",
          "growth": "-1000"
        },
        {
          "title": "三国：关于错认吕布当岳父这件事",
          "growth": "-6000"
        }
      ],
      "summary": "**🔥 题材趋势** 大唐背景持续霸榜，围绕“太宗-太子”关系的“太子文学”成为爆款公式，前五名中独占四席。同时，以袁绍、安禄山等反派或败者为主角的“翻案文”开始涌现，为历史题材提供了新切入点。\n**📖 读者偏好** 读者对轻松、反差的“谐谑”风格接受度极高，如认错吕布当岳父、劝李世民别当皇帝等。纯粹的权谋争霸退居次位，强设定+强戏剧冲突的切入点更具吸引力。\n**🆕 新上榜作品**《亡国后，女诸侯们争着抢我》，以“女追男”和“逆推”为卖点，融合了古风轻小说与多女主元素，在男性向历史文中开辟了差异化赛道。\n**📉 掉出榜单**《冒名当县令，错把始皇当亲爹》作为秦汉题材，在细分领域表现后劲不足。当前市场对秦汉热度远低于大唐，读者注意力被更集中的“大唐宇宙”吸走。\n**💡 值得关注**《大明：天启不死，大明不灭》作为唯二登榜的明朝作品，且采用“重生+争霸”的经典模式，反映了读者对“挽天倾”式救世情节的稳定需求。"
    },
    "战神赘婿": {
      "new_count": 0,
      "dropped_count": 0,
      "new_books": [],
      "dropped_books": [],
      "top_risers": [
        {
          "title": "出门捡垃圾，我被美女总裁强推了",
          "change": "+4"
        },
        {
          "title": "上门女婿也风流",
          "change": "+3"
        },
        {
          "title": "我在洛杉矶救的美女总裁",
          "change": "+1"
        }
      ],
      "top_fallers": [
        {
          "title": "殿主归来，女儿竟被骂野种",
          "change": "-2"
        },
        {
          "title": "入狱七年，出狱时整个都市都慌了",
          "change": "-2"
        },
        {
          "title": "你们选假儿子，断亲后悔干什么",
          "change": "-1"
        }
      ],
      "reads_growth": [
        {
          "title": "真当我是癞蛤蟆，离婚你又哭什么",
          "growth": "+2000"
        },
        {
          "title": "走出女子学院，从此权势滔天",
          "growth": "+1000"
        },
        {
          "title": "隐匿十年，从救下女局长开始扫黑",
          "growth": "+24"
        }
      ],
      "summary": "**🔥 题材趋势** 该赛道已高度“内卷”，核心套路固化：“兵王/神医/狱尊”回归都市，扮猪吃虎、打脸反派、被美女总裁倒追。榜单前二十名几乎全是这类模板的微调，创新乏力。\n**📖 读者偏好** 读者追求极致、直接的爽感，对“身份隐瞒-被迫展示-全场震惊”的循环剧情乐此不疲。离婚、退婚、被瞧不起的“起-落”结构是标配，重点在于“打脸”的力度和频率。\n**🆕 新上榜作品** 无。榜单头部作品固化，新人新书难以撼动既有格局。这反映出该品类流量红利趋于饱和，用户阅读习惯高度集中在少数头部作者。\n**📉 掉出榜单** 无。如同“人员零变动”，说明该品类内部流动性极差，市场缺乏活力。长期来看，若不出现题材上的重大突破，该分类将面临增长瓶颈。\n**💡 值得关注**《入伍说好做兄弟，退役怎么被拿下》上榜第五，以“女子特战队”和“女角色追夫”为变体，为硬汉兵王文增加了情感拉扯和群像看点，是破局的有益尝试。"
    },
    "都市种田": {
      "new_count": 2,
      "dropped_count": 2,
      "new_books": [
        "入狱六年，我的股票暴涨一千倍",
        "重生1984从分房开始改写人生"
      ],
      "dropped_books": [
        {
          "title": "1988到2049从卖荔枝发家",
          "intro": "（1988+年代怀旧+随身空间+荔枝+发家致富+创业+励志+人间烟火+科技+财富+文娱+华娱+多女+跨界） 李宇从2026穿越到1988年的深圳，拥有可以保鲜，保质的随身空间。 除此之外，李宇还发现自"
        },
        {
          "title": "重生1985：我上清北你急啥？",
          "intro": "重生1985，未婚妻考上师范大学要退婚。 王凯：退婚可以，八百块彩礼，一分不能少。没钱？打欠条。 重生一回，他不再当冤大头。 复读、控分、上清北，顺便投喂同桌宋若涵。 大院小花平时像只小鹌鹑，低头不说"
        }
      ],
      "top_risers": [
        {
          "title": "穿六零港岛，开局搬空老美金库",
          "change": "+7"
        },
        {
          "title": "年代：每日情报开局截胡女儿国王",
          "change": "+7"
        },
        {
          "title": "港岛1980：从夫人怀孕开始！",
          "change": "+4"
        }
      ],
      "top_fallers": [
        {
          "title": "下乡年代：十二个绝美知青宠养我",
          "change": "-5"
        },
        {
          "title": "捡了毒贩两个亿",
          "change": "-3"
        }
      ],
      "reads_growth": [
        {
          "title": "从1959开始，年代生活气息！",
          "growth": "+3000"
        },
        {
          "title": "渔猎北大荒1958",
          "growth": "+1000"
        }
      ],
      "summary": "**🔥 题材趋势** 重回“年代”是绝对主流，榜单前二十中超过一半是80、60、50年代背景的种田/发家文。题材进一步细分，从“赶海”、“打猎”到“炒股”、“港岛风云”，元素组合愈发多样。\n**📖 读者偏好** 读者对“信息差”带来的金手指爽感需求旺盛，如重回过去利用时代红利（世界杯、房地产、股票）、或是拥有系统（海洋图鉴、种植系统）。轻松、日常、搞笑是基调，“重甜轻虐”趋势明显。\n**🆕 新上榜作品**《入狱六年，我的股票暴涨一千倍》和《重生1984从分房开始改写人生》。前者是“蒙冤-隐忍-逆袭”的经典路径，后者则切入更细的“分房”痛点，反映了读者对特定年代下“体制内生存”题材的共鸣。\n**📉 掉出榜单**《1988到2049从卖荔枝发家》和《重生1985：我上清北你急啥？》。前者跨度太大，设定厚重感与快速更新的网文节奏可能冲突；后者退婚理由偏日常，爽点不够尖锐，在激烈竞争中掉队。\n**💡 值得关注**《穿六零港岛，开局搬空老美金库》和《年代：每日情报开局截胡女儿国王》排名大幅上升。前者将“港岛黑帮”与“死士金手指”结合，后者则融合了“猎艳”和“系统”，都证明了“年代+”复合题材的吸引力。"
    },
    "传统玄幻": {
      "new_count": 1,
      "dropped_count": 1,
      "new_books": [
        "我都成反派了，女主还往我怀里钻"
      ],
      "dropped_books": [
        {
          "title": "阴阳鼎",
          "intro": "我有一鼎，可纳阴阳。 　　我有一鼎，可容万界。 　　我有一鼎，可炼天地。 　　我有一鼎，可定生死。 　　我有一鼎，可断因果。 　　我有一鼎，可镇诸天。 　　我有一鼎，可安众生。 　　我有一鼎，可爱己身"
        }
      ],
      "top_risers": [
        {
          "title": "替师兄成亲后，我被师姐缠上了",
          "change": "+4"
        },
        {
          "title": "妖狐书生：从进京赶考开始",
          "change": "+3"
        },
        {
          "title": "南部档案：麒麟照山海",
          "change": "+2"
        }
      ],
      "top_fallers": [
        {
          "title": "实力比老祖恐怖，你竟敢诬陷我？",
          "change": "-6"
        },
        {
          "title": "开局喜当爹，我和美女剑仙有个娃",
          "change": "-3"
        },
        {
          "title": "女尊：惹到未婚妻我被对方囚禁了",
          "change": "-2"
        }
      ],
      "reads_growth": [
        {
          "title": "我对着红旗唱歌，它飘起来了",
          "growth": "+1000"
        },
        {
          "title": "开局喜当爹，我和美女剑仙有个娃",
          "growth": "-1000"
        },
        {
          "title": "戍边十年归，一念镇国，弹指斩天",
          "growth": "-3000"
        }
      ],
      "summary": "**🔥 题材趋势** 退婚流与反套路设定成为主流，TOP1《开局法相，未婚妻不退婚》以近40万在读断层领先，验证了读者对“主角非天命”设定的高接受度。同时，神话历史元素（如《神话三国》）与末日红旗信仰（如《我对着红旗唱歌》）开始渗透传统玄幻，题材融合趋势明显。\n\n**📖 读者偏好** 爽感与逆袭是核心，关键词“无敌”“杀伐果断”“多女主”高频出现。读者对“系统”“法相”等金手指设定依赖度高，偏好高概念、快节奏的开局。传统仙侠的慢热叙事正在让位于强冲突、高爆点的“开局即高潮”模式。\n\n**🆕 新上榜作品** 《我都成反派了，女主还往我怀里钻》聚焦“重生反派”视角，延续了网文界对“反派文”的探索，利用主角对剧本的预知制造反差爽感，符合读者对解构传统“正道”的心理偏好。\n\n**📉 掉出榜单** 《阴阳鼎》掉出榜单，表明读者对“我有一鼎”式、缺乏新颖高概念的套路化法宝设定已产生审美疲劳。\n\n**💡 值得关注** 《替师兄成亲后，我被师姐缠上了》排名逆势上升+4，其“多女主+病娇+黑化”的元素组合，在传统玄幻中开辟了“强制爱”的细分赛道，显示出读者对情感关系复杂度和边缘性趣味的高需求。"
    },
    "历史脑洞": {
      "new_count": 1,
      "dropped_count": 1,
      "new_books": [
        "糟糕，我的副本被历朝帝王曝光了"
      ],
      "dropped_books": [
        {
          "title": "五代：吨级铁骑平乱世开太平",
          "intro": "【五代】【乱世】【降维打击】【割据自立】 李青穿越五代后晋开运三年。 此时正值中原与契丹第三次大战，杜重威投降前夕。 即将神州陆沉，契丹铁骑肆虐中原前夜。 金手指很牛批，玄甲傀儡系统，每日一骑，刀枪不"
        }
      ],
      "top_risers": [
        {
          "title": "大秦：摆烂九皇子被天幕曝光",
          "change": "+4"
        },
        {
          "title": "大明：每天获得一个神通",
          "change": "+3"
        },
        {
          "title": "本是大明第一贪，嘉靖夸我是好官",
          "change": "+3"
        }
      ],
      "top_fallers": [
        {
          "title": "修仙皇帝：开局曝光我儿圣君",
          "change": "-3"
        },
        {
          "title": "大明魔丸：请陛下称太孙！",
          "change": "-2"
        },
        {
          "title": "天幕直播语文课，古人破防了",
          "change": "-2"
        }
      ],
      "reads_growth": [
        {
          "title": "大秦我带秦始皇长生不老",
          "growth": "+2.0万"
        },
        {
          "title": "本是大明第一贪，嘉靖夸我是好官",
          "growth": "+7000"
        },
        {
          "title": "大秦：摆烂九皇子被天幕曝光",
          "growth": "+4000"
        }
      ],
      "summary": "**🔥 题材趋势** 天幕、系统、签到等现代元素深度参与历史叙事成为绝对主流，TOP1《我被老朱问斩》和大秦、大唐等热门朝代作品均依赖此模式。不是严肃考据，而是通过“现代知识降维打击”制造爽点，尤其是对历史名人（朱元璋、李世民、秦始皇）的颠覆性解构引发共鸣。\n\n**📖 读者偏好** 读者对“父子互坑”“对掏”“造反”等幽默冲突桥段有极高的包容度和喜爱度，轻松搞笑、颠覆历史的“梗文”优于严肃权谋。同时，“强国”与“拯救名将名臣”的家国情怀基底仍是读者情感共鸣点。\n\n**🆕 新上榜作品** 《糟糕，我的副本被历朝帝王曝光了》是典型的“副本+万朝”模式，将现代游戏概念打包给古人，通过资源交易和跨时空联动的脑洞制造爽感，精准击中了读者对“降维打击”和“全古人震惊”叙事的偏好。\n\n**📉 掉出榜单** 《五代：吨级铁骑平乱世开太平》作为传统争霸文，因缺乏系统、天幕等现代脑洞元素而动力不足，在快节奏、高创意的榜单竞争中难以维持热度。\n\n**💡 值得关注** 《本是大明第一贪，嘉靖夸我是好官》排名上升+3，作品将“系统”与“贪官”结合，靠“合法贪腐”架空历史，这种“反套路”的体制内生存指南，为历史文提供了新鲜视角，具备破圈潜质。"
    },
    "悬疑脑洞": {
      "new_count": 1,
      "dropped_count": 1,
      "new_books": [
        "女儿特长填盗墓，我被国家找上门"
      ],
      "dropped_books": [
        {
          "title": "全民学校求生：所有学校沦为地狱",
          "intro": "【学校求生】【末世】【微群像】【不无脑】【不圣母】【半无限流】【S级天赋隐身虚化】【多】 现在的大学，形式主义极其严重。 顾平生本来是想帮导员，找行政黄老师盖某个文件章，却被黄老师各种理由搪塞阻碍，甚"
        }
      ],
      "top_risers": [
        {
          "title": "扒皮鬼",
          "change": "+5"
        },
        {
          "title": "盗墓：背棺送葬，奖励龙象般若功",
          "change": "+4"
        },
        {
          "title": "全民恐怖求生：我觉醒加点序列！",
          "change": "+4"
        }
      ],
      "top_fallers": [
        {
          "title": "盗墓：满级听雷师，铁三角人麻了",
          "change": "-8"
        },
        {
          "title": "人在盗墓世界，从张家放野开始",
          "change": "-4"
        },
        {
          "title": "末世，开局提前觉醒三大神级异能",
          "change": "-2"
        }
      ],
      "reads_growth": [
        {
          "title": "外卖撞鬼：开局抽到雷电法王石坚",
          "growth": "+8000"
        },
        {
          "title": "盗墓：满级出棺，带飞铁三角",
          "growth": "+5000"
        },
        {
          "title": "诸天恐怖：我以旁门左道杀穿万界",
          "growth": "+2000"
        }
      ],
      "summary": "**🔥 题材趋势**  \n盗墓、诡异复苏、系统流仍为主流，其中“盗墓+带飞铁三角”模式扎堆（4本在榜），重生+末世/诡异开局亦高频出现。  \n\n**📖 读者偏好**  \n偏好“系统+无敌”金手指驱动的爽文节奏，悬疑元素仅作背景，实质追求轻松、反套路、高爆发的阅读体验。  \n\n**🆕 新上榜作品**  \n《女儿特长填盗墓，我被国家找上门》：以“幼儿职业填表”触发国家召集的荒诞开局，差异化切入盗墓题材。  \n\n**📉 掉出榜单**  \n《全民学校求生：所有学校沦为地狱》：疑似因“学校+求生”题材同质化严重，且缺乏新意，被读者快速淘汰。  \n\n**💡 值得关注**  \n《扒皮鬼》+5位：纯正传统灵异、重恐反转风格，在系统爽文堆中形成稀缺性，验证硬核悬疑仍有空间。  \n《外卖撞鬼：开局抽到雷电法王石坚》：将日常职业与灵异抽卡结合，设定轻快新鲜，留存潜力较高。"
    },
    "都市脑洞": {
      "new_count": 1,
      "dropped_count": 1,
      "new_books": [
        "说好免费游戏，你满屏充值入口？"
      ],
      "dropped_books": [
        {
          "title": "都2026了，还怎么多子多福？",
          "intro": "【多子多福】【去医院500次】【社会群像】【神豪】【都市异能】 三十岁一事无成，光棍，社畜，摆烂，打算躺平老了做五保户，被亲爹扇耳光骂不孝。 直到觉醒多子多福系统。 可是，都2026年了，他一个连八离"
        }
      ],
      "top_risers": [
        {
          "title": "都要退圈了，你演唱会唱这么红？",
          "change": "+6"
        },
        {
          "title": "写个情书而已，我真不是大文豪！",
          "change": "+5"
        },
        {
          "title": "神豪太青涩，校花闺蜜团只好倒追",
          "change": "+4"
        }
      ],
      "top_fallers": [
        {
          "title": "表哥喊我上五哈，哈妮克姿赖上我",
          "change": "-8"
        },
        {
          "title": "上恋综后，和清冷设计师爆火全网",
          "change": "-2"
        },
        {
          "title": "什么叫高考满分，但人失踪了？",
          "change": "-1"
        }
      ],
      "reads_growth": [
        {
          "title": "神豪太青涩，校花闺蜜团只好倒追",
          "growth": "+6000"
        },
        {
          "title": "我一写网文的，你让我混娱乐圈？",
          "growth": "-7000"
        },
        {
          "title": "写个情书而已，我真不是大文豪！",
          "growth": "-1.2万"
        }
      ],
      "summary": "**🔥 题材趋势** 神豪/暴富躺平、系统/游戏化、娱乐圈/综艺、重生/穿越仍是核心爆款引擎。教师、程序员等职业背景与“系统”“开局”结合，催生新变体；情感向作品（青梅竹马、恋综）表现稳定。\n**📖 读者偏好** 极度青睐“开局即爽”的强设定和快节奏打脸，偏好不压抑、带幽默感的“乐子人”主角。对“躺赢”、“认知差”和“反套路”设定接受度高。\n**🆕 新上榜作品** 《说好免费游戏，你满屏充值入口？》以“游戏开发+黑心老板”的独特反套路喜剧，切入核心爽点，开局亮眼。\n**📉 掉出榜单** 《都2026了，还怎么多子多福？》热度消退，可能因“多子多福”题材在当前“躺平”风潮下，与读者追求的个人解脱感产生错位。\n**💡 值得关注** 《写个情书而已，我真不是大文豪！》排名飙升，证明“高甜+修罗场”的青春文豪题材爆发力强；《表哥喊我上五哈》排名骤降，显示综艺类题材竞争激烈，需持续高能情节维持读者新鲜感。"
    },
    "玄幻脑洞": {
      "new_count": 4,
      "dropped_count": 4,
      "new_books": [
        "从成为一只白鹿开始的传说",
        "开局境界全族总和，打造不朽帝族",
        "晚年被弟子背刺，重生我黑化了",
        "人在魔宗，让我当完美大师兄？"
      ],
      "dropped_books": [
        {
          "title": "无敌体验到期后抢来的道侣要杀我",
          "intro": "无敌体验卡到期后，王一剑从化神大圆满跌落至凡人境界，但修为每年保底增长一个大境界，飞升，只需七年，可他觉得太慢，直接将系统升至疯狂版，只需完成指定任务就能快速增长修为，可系统每次给出的任务都让他难以抉"
        },
        {
          "title": "洪荒人教首徒，你一境一个金词条",
          "intro": "穿越洪荒，成为了女娲刚刚捏土造出不久的先天人族玄都。 此时正值巫妖量劫前期，大罗满地走，太乙不如狗，人族如同草芥，随时可能在两族冲突中覆灭。面对这毫无背景的地狱开局，玄都成功觉醒了境界突破词条系统。 "
        },
        {
          "title": "词条修仙：开局天灵根，一年一抽",
          "intro": "【词条+修仙+天才+开局天灵根】 穿越到修仙世界，苏云掏空积蓄参加青云宗招徒大典，受尽旁人嘲讽轻视，所有人都认定他不过是底层蝼蚁。 可谁料测灵台上，他竟测出百万中无一的天灵根。 紧接着，【词条系统】骤"
        },
        {
          "title": "开局真太监，帮皇帝传宗接代",
          "intro": "“叮，冷宫打卡五年，系统开启！” “天命大反派系统绑定成功。” “任务刷新【开枝散叶】，一年内拥有一名子嗣，失败惩罚：寿命减少二十年。” 林夜：我一太监你让我传宗接代？ ...... 五十年后，二皇子"
        }
      ],
      "top_risers": [
        {
          "title": "低调皇子，开局召唤内务府练习生",
          "change": "+3"
        },
        {
          "title": "死一次加一点，女帝圣女全破防",
          "change": "+1"
        }
      ],
      "top_fallers": [
        {
          "title": "洪荒天幕：开局曝光十亿神话大罗",
          "change": "-5"
        },
        {
          "title": "满门都是天骄，我真不想当魅魔啊",
          "change": "-3"
        },
        {
          "title": "明日校场领响，我每日功法大圆满",
          "change": "-3"
        }
      ],
      "reads_growth": [
        {
          "title": "玄幻：从三岁开始，就跟我爹走镖",
          "growth": "-6000"
        },
        {
          "title": "绣球你都接了，还说不是我相公？",
          "growth": "-2.1万"
        }
      ],
      "summary": "**🔥 题材趋势** 传统修仙框架为基底，融合“系统”、“面板”、“签到”等工具流，另辟蹊径的“家族流”、“重生黑化”、“人皇/天骄”是当前主流。动物主角（白鹿）和特殊身份（大哥、太监）开始崭露头角。\n**📖 读者偏好** 偏爱“无敌流”和“体系化”的成长路径。对“一日破五境”的数值快感、“被背刺后黑化”的情绪反转、“打造不朽帝族”的积攒式满足有较高黏性。追求明确、简单的升级目标和获得感。\n**🆕 新上榜作品** 四部新作风格差异显著，《从成为一只白鹿开始的传说》以动物主角和灵韵点系统切入，创意独特；《开局境界全族总和》与《晚年被弟子背刺》则分别代表了“族群共创”和“复仇黑化”两大趋势。\n**📉 掉出榜单** 《洪荒人教首徒》等洪荒类作品热度下降，显示读者对宏大背景产生了审美疲劳，转而追求更“小而美”或更“反套路”的世界观设定。\n**💡 值得关注** 《从成为一只白鹿开始的传说》口碑与在读双高，证明“异类主角”在玄幻有巨大潜力；《开局境界全族总和，打造不朽帝族》将个人成长与家族绑定，开创了新的“团战式爽感”，需观察能否成为新流派。"
    },
    "悬疑灵异": {
      "new_count": 1,
      "dropped_count": 1,
      "new_books": [
        "恐怖漫画家：让噩梦人间复苏"
      ],
      "dropped_books": [
        {
          "title": "风水之王，这个道爷下山镇百鬼",
          "intro": "李长生天生纯阳焚命格，每逢初八天火焚身，唯有寻纯阴女子泄洪方能活命。 可下山后他才发现，那个命定的女人，竟是百年邪术的祭品，为了破局，他拔剑出鞘，管他神佛妖魔，一剑斩之！"
        }
      ],
      "top_risers": [
        {
          "title": "娶了警花，她天天怀疑我是悍匪",
          "change": "+7"
        },
        {
          "title": "菜鸟队长身边全是刑侦高手",
          "change": "+3"
        },
        {
          "title": "南部档案：开局青龙血脉镇压邪神",
          "change": "+3"
        }
      ],
      "top_fallers": [
        {
          "title": "罪案现场，那些轰动全国的大案",
          "change": "-4"
        },
        {
          "title": "盗墓笔记：秦始皇陵",
          "change": "-2"
        },
        {
          "title": "我妈死后，我回村给自己办葬礼",
          "change": "-2"
        }
      ],
      "reads_growth": [
        {
          "title": "完美犯罪？在我的眼里全是破绽！",
          "growth": "+2.8万"
        },
        {
          "title": "夜半守坟，活人借命",
          "growth": "+7000"
        },
        {
          "title": "菜鸟队长身边全是刑侦高手",
          "growth": "+1000"
        }
      ],
      "summary": "**🔥 题材趋势**  \n刑侦破案类集中发力，“系统”与“犯罪心理”成为高频设定。盗墓、民俗灵异与纪实大案为辅线，系统流、轻爽文仍是主流快车道。\n\n**📖"
    },
    "抗战谍战": {
      "new_count": 1,
      "dropped_count": 1,
      "new_books": [
        "抗战：军校留学生，资历拉满！"
      ],
      "dropped_books": [
        {
          "title": "抗战：开局长津湖，杀穿全战场",
          "intro": "【热血抗战+保家卫国】 陈枫穿到抗战融合的世界，成了一个名不见经传的路人甲。 好消息：绑定了一个快穿军神系统！ 坏消息：但这金手指不是来享福的，是来上强度的，而且开局就把他送去了长津湖。"
        }
      ],
      "top_risers": [
        {
          "title": "抗战：从家仆到功德林头等战犯",
          "change": "+9"
        },
        {
          "title": "亮剑：开局自爆系统，直升旅长",
          "change": "+5"
        },
        {
          "title": "辽东沦丧前夜，率军兵谏少帅",
          "change": "+2"
        }
      ],
      "top_fallers": [
        {
          "title": "监狱觉醒：我率红七军团北上抗日",
          "change": "-7"
        },
        {
          "title": "军阀老爹不争气，我死战不退！",
          "change": "-5"
        },
        {
          "title": "抗战：伪军连长？不，我代号薪火",
          "change": "-2"
        }
      ],
      "reads_growth": [
        {
          "title": "辽东沦丧前夜，率军兵谏少帅",
          "growth": "+1.9万"
        },
        {
          "title": "亮剑：太爷穿我家，无限火力支援",
          "growth": "+6000"
        },
        {
          "title": "亮剑：开局自爆系统，直升旅长",
          "growth": "+4000"
        }
      ],
      "summary": "**🔥 题材趋势** 榜单呈现“经典IP活化”与“金手指重度化”并存的特点。《亮剑》、《四合院》等老IP的二次创作占据头部，且大量作品融合系统、双穿、现代物资流等元素，传统硬核谍战题材占比下降。\n**📖 读者偏好** 读者对“非AI”手工作品的需求明确（如榜首作品简介强调），同时偏好“轻松搞笑”与“杀伐果断”两种截然不同的情绪体验。具备明确金手指（系统、空间）和清晰升级路径的作品更易获得高在读。\n**🆕 新上榜作品** 《抗战：军校留学生，资历拉满！》凭借“双料资历”（国共两党+留洋）的独特人设切入市场，迎合了读者对“根正苗红+专业过硬”主角的期待。\n**📉 掉出榜单** 《抗战：开局长津湖，杀穿全战场》掉榜，表明单纯依靠“杀穿”的直白爽点，在缺乏新鲜设定支撑时，竞争力容易被同质化作品稀释。\n**💡 值得关注** 排名上升最快的《抗战：从家仆到功德林头等战犯》，其“从底层到战犯”的反差叙事路径，以及“无系统”的标签，在系统文泛滥的当下形成了差异化竞争力。"
    },
    "游戏体育": {
      "new_count": 3,
      "dropped_count": 3,
      "new_books": [
        "CS：被拒签后，我成为冠军教练",
        "木筏求生，开局捡到国民女神",
        "NBA：魔术师模板，抢乐邦状元"
      ],
      "dropped_books": [
        {
          "title": "开局sss级天赋，我坦度超标",
          "intro": "（评分刚出!会慢慢涨回来的!）【网游】【一点群像】【无女主】 《天运》 一款划时代的游戏，吸引了无数人进入，被称为第二世界。 秦山一进入游戏，发现自己获得了sss级天赋，所有的主动技能都被转化成了被动"
        },
        {
          "title": "科比超乔丹，大姚是常务副山羊？",
          "intro": "【评分刚出，后续必涨】 【NBA+经理+开局+大姚+科比】 谁是NBA历史最伟大的球员？ 那肯定是我说的算！ 2004年，身为铁杆球迷的陈宇重生成为湖人队的总经理。 交易奥尼尔，换来大姚！ NBA历史"
        },
        {
          "title": "游戏入侵：我能无限装备",
          "intro": "（评分刚出，会涨的） 【游戏入侵】+【装备无限】+【套装叠加】+【第四天灾】+【轻松搞笑】 游戏直接入侵了，降临现实，全民进入末日倒计时。 陆观之没重生，没穿越，没参加什么内测，就是个突然被卷入的普通"
        }
      ],
      "top_risers": [
        {
          "title": "足球：离开国奥，我成了中场暴君",
          "change": "+2"
        },
        {
          "title": "NBA：满级青峰，带着大姚夺冠",
          "change": "+2"
        },
        {
          "title": "LOL：直播圈米顺便扬名立万",
          "change": "+2"
        }
      ],
      "top_fallers": [
        {
          "title": "三角洲：你这干员合法吗？",
          "change": "-3"
        },
        {
          "title": "魔王游戏：开局让财阀千金恶堕",
          "change": "-1"
        }
      ],
      "reads_growth": [
        {
          "title": "三角洲：我一扶贫主播却被喊CS",
          "growth": "+1.1万"
        },
        {
          "title": "足球：开局被断腿，搭档哈兰德！",
          "growth": "+3000"
        },
        {
          "title": "嘉豪三角洲：从裸枪清图开始成神",
          "growth": "-1000"
        }
      ],
      "summary": "**🔥 题材趋势** 体育竞技（足球、NBA）与游戏直播（三角洲、LOL）双线并行，且“系统”几乎是标配。NBA与足球题材大量使用“黑子的篮球”等动漫模板，网文圈层融合趋势明显。\n**📖 读者偏好** 读者对“职业化”路径有强烈偏好（如加入德甲、进入KPL），并喜爱“逆袭打脸”+“夸张技术（系统）”的爽感组合。同时，“搞笑整活”和“直播互动”元素能有效提升作品亲和力。\n**🆕 新上榜作品** 《CS：被拒签后，我成为冠军教练》切中了相对空白的“教练文”细分赛道，以高概念人设（冠军选手转型教练）和“调教”现役选手的爽点吸引硬核电竞读者。\n**📉 掉出榜单** 《开局sss级天赋》、《科比超乔丹》等传统网游/体育文掉榜，显示单一的天赋堆砌或名人对比已难以维持热度，读者需要更具体的叙事钩子或系统玩法。\n**💡 值得关注** 新上榜的《木筏求生，开局捡到国民女神》跨品类流入，表明“生存+擦边”的基因在体育游戏分类中仍有渗透空间，但其长线留存能力有待观察。"
    },
    "动漫衍生": {
      "new_count": 3,
      "dropped_count": 3,
      "new_books": [
        "铠甲：捡到封魔盒后，我不吃牛肉",
        "咒回：特级的我去打万业尸仙了",
        "咒回：疼痛换积分？太阴间了吧！"
      ],
      "dropped_books": [
        {
          "title": "超神：由我编造的IF线",
          "intro": "天河战役 当饕餮降临，第一次上战场的雄兵连慌忙上阵 银河之力开始录制遗言 蕾娜即将被弑神长矛击中 一声怒吼响起 “德玛西亚！\" 下一秒，一道手拿巨剑的高大身影挡在了蕾娜的前方 “好久不见，大姐头” ”"
        },
        {
          "title": "天幕：开局短视频锐评木叶村民",
          "intro": "【火影】【无主角】【盘点】 忍界，天空出现一块巨大的天幕。 开局锐评木叶村民 【不为强大而屈服】 【不因胆怯而退缩】 【越强大我越80】 【越危险我越贴脸】 两天秤大野木：“不为强大而屈服……这真的是"
        },
        {
          "title": "崩铁国运：您的币战通天代已上线",
          "intro": "【崩铁】+【货币战争】+【平行世界国运】 分刚出，可能会涨，保证入股不亏 后期有崩铁角色降临。 国运系统突然降临平行世界，擂台战竟然是各个国家抽取选手上台直播玩货币战争崩铲铲？！ 赢了的国家可抽取诸多"
        }
      ],
      "top_risers": [
        {
          "title": "咒回：魔虚萝不想成为弱者思维",
          "change": "+3"
        },
        {
          "title": "一人：龙虎山保安，拦哭十佬！",
          "change": "+3"
        },
        {
          "title": "星铁：我的沙雕网友竟然是小浣熊",
          "change": "+2"
        }
      ],
      "top_fallers": [
        {
          "title": "八极星上，我觉醒了十二符咒",
          "change": "-11"
        },
        {
          "title": "三角洲：我有1哈夫币秒杀系统！",
          "change": "-3"
        },
        {
          "title": "原神：开局负债，无奈成为执行官",
          "change": "-3"
        }
      ],
      "reads_growth": [
        {
          "title": "一人：武侯奇门不在奇门，在武侯",
          "growth": "+1.0万"
        }
      ],
      "summary": "**🔥 题材趋势** 头部作品高度集中，主要围绕《一人之下》、《咒术回战》、《原神》、《崩铁》四大IP展开，且“系统”和“扮演”成为核心驱动力。同质化竞争激烈，细分设定（如植物、魔虚萝）是脱颖而出的关键。\n**📖 读者偏好** 读者偏好“战力颠覆”和“反套路”内容，如《一人：武侯奇门不在奇门》强调“维稳”而非“争霸”，《咒回：魔虚萝》化用流行梗。轻松、搞笑、日常向的叙述风格更受欢迎。\n**🆕 新上榜作品** 《咒回：特级的我去打万业尸仙了》与《咒回：疼痛换积分？太阴间了吧！》均属《咒术回战》同人，前者主打“诸天挑战爽”，后者主打“自残换战力”的阴间创意，说明该题材内部细分赛道仍有活力。\n**📉 掉出榜单** 《超神：由我编造的IF线》等“大盘点/观影体”类作品掉榜，表明流于形式的信息回顾已不能满足读者，他们需要更深度的人设重塑或剧情介入。\n**💡 值得关注** 《八极星上，我觉醒了十二符咒》排名暴跌11位，提示“冷门IP（星游记）+热门系统”的组合虽能短期吸量，但缺乏持续的内容支撑，读者流失速度很快。"
    },
    "男频衍生": {
      "new_count": 3,
      "dropped_count": 3,
      "new_books": [
        "人在一人，但是摸金校尉！",
        "名义：从接替老刘开始",
        "四合院：从志愿军开始"
      ],
      "dropped_books": [
        {
          "title": "重生祁同伟直播跳江，气哭沙瑞金",
          "intro": "前世，沙瑞金操盘，侯亮平为刀，联手逼自己饮恨孤鹰岭。 祁同伟重生归来，直接掀桌子！ 侯亮平，你不是高高在上，满口道德吗？ 我当着全网的面，撕开你虚伪胆小的真面目。 沙瑞金，你贬低我，说我是害群之马？ "
        },
        {
          "title": "穿越倚天，拜师俞莲舟！",
          "intro": "微改不魔改，弥补遗憾，节奏不拖沓，逻辑自洽，不无敌，成长型，单女主周芷若。 俞渊稀里糊涂的就穿越了，被救后俞渊拜俞莲舟为师，正式踏入江湖。 起初他也想躺平不动，但作为俞莲舟唯一的徒弟，怎么着也得给师父"
        },
        {
          "title": "黑袍压力怪，开局红温祖国人",
          "intro": "【爽文】【雄狮般的语言系统】【父慈子孝】【家庭和睦】【小嘴抹了蜜】 穿越成祖国人同父异母的亲弟弟查尔斯，自带情绪点系统。 压力别人，就能从他们身上得到情绪点，强化能力？ 那你要这么说的话，我那雄狮般的"
        }
      ],
      "top_risers": [
        {
          "title": "四合院：从李云龙战友开始",
          "change": "+6"
        },
        {
          "title": "祁同伟重生：执钟弄琴，胜天一子",
          "change": "+1"
        },
        {
          "title": "四合院：50年，我海归双料博士",
          "change": "+1"
        }
      ],
      "top_fallers": [
        {
          "title": "神雕杨过？不，是巨雕杨过",
          "change": "-3"
        },
        {
          "title": "飞驰人生：我带张弛制霸赛道",
          "change": "-3"
        },
        {
          "title": "四合院：穿越傻柱，东旭当天没了",
          "change": "-2"
        }
      ],
      "reads_growth": [
        {
          "title": "祁同伟重生：执钟弄琴，胜天一子",
          "growth": "+5.1万"
        },
        {
          "title": "神雕杨过？不，是巨雕杨过",
          "growth": "+8000"
        }
      ],
      "summary": "**🔥 题材趋势**  \n穿越、重生、系统仍是绝对主流，同人衍生（四合院、人民的名义、龙族）高度扎堆。其中“四合院”类近半，核心套路为“逆袭打脸禽兽”；“名义”类聚焦官斗与改变悲剧命运。\n\n**📖 读者偏好**  \n追求“爽文”体验，偏好强金手指（签到/系统/双重身份），偏爱“杀伐果断”“改变原著悲剧”的逆袭叙事，反感憋屈与拉扯。\n\n**🆕 新上榜作品**  \n- 《人在一人，但是摸金校尉！》：跨世界融合“盗墓+鉴宝+一人之下”，品类混搭有差异化。  \n- 《名义：从接替老刘开始》：以“替代梁璐目标”切入，提供全新视角的老剧新编。  \n- 《四合院：从志愿军开始》：从历史战争过渡到四合院，背景融合增加新鲜感。\n\n**📉 掉出榜单**  \n- 《重生祁同伟直播跳江》（名义类）、《穿越倚天，拜师俞莲舟！》（武侠类）、《黑袍压力怪》（超英类）均因题材相对小众或同质化严重，被更稳定的“四合院”和“名义”类挤压。\n\n**💡 值得关注**  \n- 《人在一人，但是摸金校尉！》：突破单一衍生框架，将“一人之下”与盗墓探险结合，系统触发机制（墓穴打卡）具备新鲜感。  \n- 《斩神"
    }
  }
}